Workbook

Sheet PORTADA
B2: MOBIJUESA S.A. — FLUJO DE CAJA SEMANAL VIVO
B3: Proyección semanal SEM 37 a SEM 52 de 2026 (07-sep al 27-dic) — control, gestión y solicitud de fondeo
B5: Corte de datos: 07-sep-2026. Reemplaza en alcance (no en archivo) a 'FLUJO DE CAJA MOBIJUESA - ACTUALIZADO AL 14-AGO-2026.xlsx' — ese archivo queda como historial.
B7: LA CAJA HOY
B8: Saldo real de caja — Banco Pichincha, 04-sep-2026 (único banco operado) | C8: 19669.46
B9: Ingreso operativo semanal estimado (promedio real 6 meses, ene-jun 2026) | C9: 6089.59
B10: Egresos fijos semanales identificados por categoría (ver PARAMETROS) | C10: 3818.26
B11: Generación operativa NETA semanal (antes de obra) | C11: 2271.33
B12: Caja mínima de seguridad (1,5× gasto fijo mensual, recalculada por categoría) | C12: 24885.54
B13: Colchón sobre el mínimo, HOY | C13: -5216.08
B14: Ritmo histórico de gasto en obra (jul-ago 2026) | C14: 10088.13
B16: HALLAZGO PRINCIPAL DE ESTA ACTUALIZACIÓN
B17: Al desagregar los egresos fijos en sus categorías reales (gasto operativo, mantenimiento de
B18: bodegas en operación, impuestos/prediales, servicio de deuda, estudios y retiros de socios
B19: normalizados) en vez de usar un solo promedio agregado, el gasto fijo mensual real es más alto
B20: de lo que se venía usando: $16.590,36/mes en vez de $12.448,23/mes. La caja mínima de seguridad
B21: (1,5× ese gasto fijo) sube a $24.885,54 — y la caja real de hoy ($19.669,46) queda POR DEBAJO de
B22: ese mínimo: el colchón de seguridad está en NEGATIVO ($5.216,08), no 'casi agotado' como se leía
B23: en el corte del 06-sep (colchón positivo de $997,11 en ese momento, con el agregado anterior).
B25: Esto NO cambia la conclusión de fondo — ya se sabía que la obra corre muy por encima de lo que la
B26: operación genera — pero la hace más urgente: hoy, con este criterio más completo, Mobijuesa ya
B27: está operando por debajo de su propio piso de seguridad. Ver hoja RESUMEN Y ALERTA.
B29: CÓMO ESTÁ ORGANIZADO ESTE ARCHIVO
... B33: RESUMEN Y ALERTA — Vista gerencial: posición de caja, cupo de inversión sostenible, y cuánto y cuándo pedir a Agroaéreo.

Sheet INSTRUCTIVO CPA
B2: INSTRUCTIVO PARA QUIEN ALIMENTA ESTE ARCHIVO (CPA / CONTABILIDAD)
B4: 1. QUÉ ACTUALIZAR CADA DÍA
B5: • Revise el movimiento bancario del día en el Banco Pichincha (única cuenta operada).
B6: • Si hubo un COBRO de cliente, súmelo a 'Ingreso operativo estimado' de la semana en curso en la
B7: hoja FLUJO SEMANAL — reemplace la fórmula por el valor real acumulado de la semana cuando la
B8: semana cierre (viernes), o llévelo como acumulado si prefiere verlo día a día.
B9: • Si hubo un PAGO, identifique primero si es un rubro de OBRA (bodegas, materiales, mano de obra,
B10: adoquinado) o un gasto FIJO (nómina, cuota de crédito, energía, alícuota, impuesto, retiro de
B11: socio). Regístrelo en la fila correspondiente de la semana correcta en FLUJO SEMANAL.
B12: • Un pago de obra que se sabe de antemano (por ejemplo, un anticipo pactado a 3 semanas) puede
B13: escribirse HOY mismo en la semana futura que corresponda — así el saldo proyectado ya lo incluye
B14: antes de que se pague, que es justamente el objetivo de este archivo.
... B97: todavía marque verde — el semáforo es semanal, la caja se mueve a diario.

Sheet PARAMETROS
A1: PARÁMETROS — única hoja donde se edita. Todo el resto del archivo calcula desde aquí.
A2: Editar solo las celdas de la columna B (o C donde se indique). Las fórmulas del resto del archivo ya apuntan aquí.
A4: 1. FECHA Y SEMANA DE CORTE
A5: Fecha de hoy / corte de datos | B5: 46272
A6: Semana ISO de arranque de la proyección | B6: 37
A7: Plazo mínimo real de gestión de fondos con Agroaéreo (días) | B7: 7
A8: Semanas de anticipación para disparar la alerta (redondeo del plazo) | B8: =ROUNDUP(B7/7,0)
A10: 2. SALDO REAL DE CAJA
A11: Saldo real Banco Pichincha (único banco operado) a la fecha de corte | B11: 19669.46 | D11: Fuente: detalle de cheques SEM36 aportado por el usuario, saldo confirmado al 04-sep-2026.
A13: 3. INGRESO OPERATIVO — promedio real 6 meses completos (ene-jun 2026, Libro Bancos maestro)
A14: Concepto | B14: Mensual USD | C14: Semanal USD (÷4,345) | D14: Nota | E14: sem 1 | F14: sem 2 | G14: sem 3 | H14: sem 4
A15: Ingreso por cobros de clientes (arriendo de bodegas) | B15: 26459.26 | C15: =B15/4.345 | D15: Reconciliado con hoja A_FLUJO_MENSUAL del archivo 14-ago (idéntico). | E15: =+B15*0.1 | F15: =+B15*0.3 | G15: =+B15*0.4 | H15: =+B15*0.2
A17: 4. EGRESOS FIJOS — por categoría, promedio real ene-jun 2026
A18: Categoría | B18: Mensual USD | C18: Semanal USD (÷4,345) | D18: Nota
A19: Gasto operativo y administrativo | B19: 3268.57 | C19: =B19/4.345 | D19: Estable mes a mes.
A20: Mantenimiento de bodegas en operación | B20: 7099.53 | C20: =B20/4.345 | D20: 🚦 Alto ene-abr por reparaciones puntuales; may-jun bajó a ~194/sem. Recalibrar con 3 meses recientes si el patrón no se repite.
A21: Impuestos, prediales y gastos bancarios | B21: 3318.25 | C21: =B21/4.345 | D21: 🚦 Estacional: alto ene-mar por predial con descuento (COOTAD); bajo en jul-ago.
A22: Servicio de deuda — Cooperativa La Nuestra | B22: 1081.5 | C22: =B22/4.345 | D22: Cuota fija mensual del préstamo a Francisco Duque, cargada a la empresa.
A23: Estudios, planos y levantamientos | B23: 275 | C23: =B23/4.345 | D23: Irregular; sube cuando hay trámites de planificación.
A24: Retiros de socios / gasto societario y legal (normalizado) | B24: 1547.51 | C24: =B24/4.345 | D24: 🚦 Excluye el retiro atípico de $20.146,55 de mayo — con ese mes el promedio sube a $4.647,35/mes. Ajustar si el retiro de mayo se repite.
A25: SUBTOTAL EGRESOS FIJOS | B25: =SUM(B19:B24) | C25: =SUM(C19:C24)
A27: 5. CAJA MÍNIMA DE SEGURIDAD
A28: Caja mínima de seguridad (1,5× egresos fijos mensuales — criterio C_CUPO_Y_ALERTA) | B28: =1.5*B25
A30: 6. OBRA — RUBROS PENDIENTES (fuente: Presupuesto Bodegas 5-9-26.xlsx, corte 06-sep-2026)
A31: Rubro | B31: Monto pendiente USD | D31: Nota
A32: Pendiente Tapia (estructura) | B32: 2784
A33: Pendiente Flores (piso, pozo séptico, emblocado) | B33: 15407.28
A34: Pendiente Chinchi (eléctrico) | B34: 2677.25
A35: Adoquinado — mano de obra | B35: 11210
A36: Adoquinado — material | B36: 22520 | D36: Negociable a crédito de proveedor 30-60-90 en vez de contado.
A37: 400 m² nuevos — cimentación y estructura (40%) | B37: 24480 | D37: Vivienda tipo 90m²/$84.000 referencial de otro frente; costo aquí es de bodega ~$153/m².
A38: 400 m² nuevos — obra civil y acabados (60%) | B38: 36720
A39: TOTAL OBRA PENDIENTE | B39: =SUM(B32:B38)
A41: 7. RECONCILIACIÓN — por qué cambió el número frente al corte del 06-sep-2026
A42: El corte anterior (hoja 'LIQUIDEZ Y CUPO' de Presupuesto Bodegas 5-9-26.xlsx) usó un solo agregado
A43: de egreso fijo mensual ($12.448,23) sobre el Libro Bancos maestro. Este archivo lo desagrega en 6
A44: categorías reales tomadas de la hoja A_FLUJO_MENSUAL del archivo guía del 14-ago — un total mayor,
A45: porque hace visibles 'mantenimiento de bodegas en operación' e 'impuestos/prediales', que antes
A46: quedaban diluidos dentro del agregado. La caja mínima de seguridad (fila 5 de esta hoja) sube de
A47: $18.672,35 (corte 06-sep) a la cifra que resulta de 1,5× el nuevo subtotal — y el colchón sobre ese
A48: mínimo, con la caja real de hoy, pasa a ser negativo. No es una noticia nueva: la obra sigue
A49: corriendo muy por encima de lo que el negocio genera — este ajuste solo lo mide con más precisión.
A51: 8. ESCENARIOS (hoja ESCENARIOS) — agregado por el espejo 26-09-2026
A52: Egreso fijo semanal según PARAMETROS (C25) | B52: =C25 | D52: Promedio real ene-jun 2026.
A53: Ingreso operativo normal de septiembre (sem 1-3, curva de la fila 15) | B53: =E15+F15+G15 | D53: Para el escenario "septiembre normal".
A54: Aporte Agroaéreo por desembolso (referencia para el estrés) | B54: 30000 | D54: Monto usado en el flujo; editable.

Sheet FLUJO SEMANAL
A1: FLUJO DE CAJA SEMANAL — SEM 37 A SEM 52 DE 2026
A2: Fórmulas vivas: edite PARAMETROS para cambiar supuestos, o escriba un valor real directo en una celda de semana para reemplazar el estimado.
A4: CONCEPTO | B4: TOTAL / META | C4: SALDO INICIAL | D4: SEM 37 | E4: SEM 38 | F4: SEM 39 | G4: SEM 40 | H4: SEM 41 | I4: SEM 42 | J4: SEM 43 | K4: SEM 44 | L4: SEM 45 | M4: SEM 46 | N4: SEM 47 | O4: SEM 48 | P4: SEM 49 | Q4: SEM 50 | R4: SEM 51 | S4: SEM 52 | T4: TOTAL PROGR. | U4: DIFEREN- CIA
A5: Semana del … al … (calendario) | D5: 07-Sep / 13-Sep | E5: 14-Sep / 20-Sep | F5: 21-Sep / 27-Sep | G5: 28-Sep / 04-Oct | H5: 05-Oct / 11-Oct | I5: 12-Oct / 18-Oct | J5: 19-Oct / 25-Oct | K5: 26-Oct / 01-Nov | L5: 02-Nov / 08-Nov | M5: 09-Nov / 15-Nov | N5: 16-Nov / 22-Nov | O5: 23-Nov / 29-Nov | P5: 30-Nov / 06-Dec | Q5: 07-Dec / 13-Dec | R5: 14-Dec / 20-Dec | S5: 21-Dec / 27-Dec
A6: SALDO INICIAL DE CAJA | D6: =PARAMETROS!$B$11 | E6: =D55 | F6: =E55 | G6: =F55 | H6: =G55 | I6: =H55 | J6: =I55 | K6: =J55 | L6: =K55 | ... S6: =R55
A7: INGRESOS
A8: Ingreso operativo estimado (clientes) | B8: ver PARAMETROS | D8: 24965.7 | E8: 7937.778 | F8: 10583.704 | G8: 5291.852 | H8: 2645.926 | I8: 7937.778 | J8: 10583.704 | K8: 5291.852 | L8: 2645.926 | M8: 7937.778 | N8: 10583.704 | O8: 5291.852 | P8: 2645.926 | Q8: 7937.778 | R8: 10583.704 | S8: 5291.852
A9: Aportes recibidos de Agroaéreo | D9: 0 | E9: 0 | F9: 0 | G9: 0 | H9: 0 | I9: 0 | J9: 0 | K9: 0 | L9: 0 | M9: 0 | N9: 0 | O9: 0 | P9: 0 | Q9: 0 | R9: 0 | S9: 0
A10: Otros ingresos (ventas, reembolsos, etc.) | D10: 0 | E10: 0 | F10: 0 | G10: 0 | H10: 0 | I10: 0 | J10: 0 | K10: 0 | L10: 0 | M10: 0 | N10: 0 | O10: 0 | P10: 0 | Q10: 0 | R10: 0 | S10: 0
A11: TOTAL INGRESOS | D11: =SUM(D8:D10) | E11: =SUM(E8:E10) | F11: =SUM(F8:F10) | G11: =SUM(G8:G10) | H11: =SUM(H8:H10) | I11: =SUM(I8:I10) | J11: =SUM(J8:J10) | K11: =SUM(K8:K10) | ... S11: =SUM(S8:S10)
A12: EGRESOS FIJOS (operativos, administrativos, legales)
A13: Gasto operativo y administrativo | D13: 0 | E13: 0 | F13: 0 | G13: =1555+100+100 | H13: 0 | I13: 0 | J13: 0 | K13: =1555+100+100 | L13: 0 | M13: 0 | N13: 0 | O13: =1555+100+100 | P13: 0 | Q13: 0 | R13: 0 | S13: =1555+100+100
A14: Mantenimiento de bodegas en operación | D14: 0 | E14: 0 | F14: 0 | G14: 0 | H14: 0 | I14: 0 | J14: 0 | K14: 0 | L14: 0 | M14: 0 | N14: 0 | O14: 0 | P14: 0 | Q14: 0 | R14: 0 | S14: 0
A15: Impuestos, prediales y gastos bancarios | D15: 0 | E15: 0 | F15: 0 | G15: 0 | H15: 0 | I15: 0 | J15: 0 | K15: 0 | L15: 0 | M15: 0 | N15: 0 | O15: 0 | P15: 0 | Q15: 0 | R15: 0 | S15: 0
A16: Servicio de deuda — Cooperativa La Nuestra | D16: 0 | E16: 1045 | F16: 0 | G16: 0 | H16: 0 | I16: 1045 | J16: 0 | K16: 0 | L16: 0 | M16: 1045 | N16: 0 | O16: 0 | P16: 0 | Q16: 1045 | R16: 0 | S16: 0
A17: Estudios, planos y levantamientos | D17: 0 | E17: 0 | F17: 0 | G17: 0 | H17: 0 | I17: 0 | J17: 0 | K17: 0 | L17: 0 | M17: 0 | N17: 0 | O17: 0 | P17: 0 | Q17: 0 | R17: 0 | S17: 0
A18: Retiros de socios / gasto societario y legal (normalizado) | D18: 0 | E18: 0 | F18: 0 | G18: 0 | H18: 0 | I18: 0 | J18: 0 | K18: 0 | L18: 0 | M18: 0 | N18: 0 | O18: 0 | P18: 0 | Q18: 0 | R18: 0 | S18: 0
A19: Alicuotas | D19: 624.59 | E19: 0 | F19: 0 | G19: 0 | H19: 624.59 | I19: 0 | J19: 0 | K19: 0 | L19: 624.59 | M19: 0 | N19: 0 | O19: 0 | P19: 624.59 | Q19: 0 | R19: 0 | S19: 0
A20: Consumo de Energia Electrica | D20: 125.88 | E20: 0 | F20: 0 | G20: 0 | H20: 0 | I20: 0 | J20: 0 | K20: 0 | L20: 0 | M20: 0 | N20: 0 | O20: 0 | P20: 0 | Q20: 0 | R20: 0 | S20: 0
A21: SUBTOTAL EGRESOS FIJOS | D21: =SUM(D13:D20) | E21: =SUM(E13:E20) | F21: =SUM(F13:F20) | G21: =SUM(G13:G20) | H21: =SUM(H13:H20) | I21: =SUM(I13:I20) | J21: =SUM(J13:J20) | K21: =SUM(K13:K20) | ... S21: =SUM(S13:S20)
A22: EGRESOS DE OBRA / CONSTRUCCIÓN — valores sugeridos al ritmo de $10.000/sem; reprograme según pagos reales
A23: Tapia (Mano de Obra estructura) Bod. 16-17 | B23: 2050.8 | D23: 2050.8 | E23: 0 | F23: 0 | G23: 0 | H23: 0 | I23: 0 | J23: 0 | K23: 0 | L23: 0 | M23: 0 | N23: 0 | O23: 0 | P23: 0 | Q23: 0 | R23: 0 | S23: 0 | T23: =SUM(D23:S23) | U23: =B23-T23
A24: Tapia (Mano de Obra 5 puertas corredizas) | B24: 9000 | D24: 2000 | E24: 1000 | F24: 1000 | G24: 1000 | H24: 1000 | I24: 1000 | J24: 1000 | K24: 1000 | L24: 0 | M24: 0 | N24: 0 | O24: 0 | P24: 0 | Q24: 0 | R24: 0 | S24: 0 | T24: =SUM(D24:S24) | U24: =B24-T24
A25: Tapia (Mano de Obra pared metalica) | B25: 4416 | D25: 0 | E25: 1324.8 | F25: 1766.4 | G25: 1324.8 | H25: 0 | I25: 0 | J25: 0 | K25: 0 | L25: 0 | M25: 0 | N25: 0 | O25: 0 | P25: 0 | Q25: 0 | R25: 0 | S25: 0 | T25: =SUM(D25:S25) | U25: =B25-T25
A26: Flores (Mano de Obra cimentación) Bod. 16-17 | B26: 1352.43 | D26: 1352.43 | E26: 0 | F26: 0 | G26: 0 | H26: 0 | I26: 0 | J26: 0 | K26: 0 | L26: 0 | M26: 0 | N26: 0 | O26: 0 | P26: 0 | Q26: 0 | R26: 0 | S26: 0 | T26: =SUM(D26:S26) | U26: =B26-T26
A27: Flores (Mano de Obra piso, emblocado) | B27: 9652.14 | D27: 0 | E27: 5515.51 | F27: 0 | G27: 4136.63 | H27: 0 | I27: 0 | J27: 0 | K27: 0 | L27: 0 | M27: 0 | N27: 0 | O27: 0 | P27: 0 | Q27: 0 | R27: 0 | S27: 0 | T27: =SUM(D27:S27) | U27: =B27-T27
A28: Flores (Mano de Obra pozo septico) | B28: 761.25 | D28: 0 | E28: 0 | F28: 761.25 | G28: 0 | H28: 0 | I28: 0 | J28: 0 | K28: 0 | L28: 0 | M28: 0 | N28: 0 | O28: 0 | P28: 0 | Q28: 0 | R28: 0 | S28: 0 | T28: =SUM(D28:S28) | U28: =B28-T28
A29: Flores (Mano de obra Const. Bodega 150m2) | B29: 2693.88 | D29: 0 | E29: =+B29*30% | F29: 0 | G29: 0 | H29: =+B29*40% | I29: 0 | J29: 0 | K29: =+B29*30% | L29: 0 | M29: 0 | N29: 0 | O29: 0 | P29: 0 | Q29: 0 | R29: 0 | S29: 0 | T29: =SUM(D29:S29) | U29: =B29-T29
A30: Tapia (Mano de obra Const. Bodega 150m2 - Metálica) | B30: 1885 | D30: 0 | E30: =+B30/3 | F30: =+E30 | G30: =+F30 | H30: 0 | I30: 0 | J30: 0 | K30: 0 | L30: 0 | M30: 0 | N30: 0 | O30: 0 | P30: 0 | Q30: 0 | R30: 0 | S30: 0 | T30: =SUM(D30:S30) | U30: =B30-T30
A31: Tapia (Materiales Const. Bodega 150m2 - Metálica) | B31: 2485.14 | D31: 0 | E31: 0 | F31: 0 | G31: 0 | H31: 0 | I31: 0 | J31: 0 | K31: 0 | L31: 0 | M31: 0 | N31: 0 | O31: 0 | P31: 0 | Q31: 0 | R31: 0 | S31: 0 | T31: =SUM(D31:S31) | U31: =B31-T31
A32: Flores (Materiales Const. Bodega 150m2) | B32: 1507.31 | D32: 0 | E32: =+B32/2 | F32: =+E32 | G32: 0 | H32: 0 | I32: 0 | J32: 0 | K32: 0 | L32: 0 | M32: 0 | N32: 0 | O32: 0 | P32: 0 | Q32: 0 | R32: 0 | S32: 0 | T32: =SUM(D32:S32) | U32: =B32-T32
A33: Hormigon - Bodega 150m2 | B33: 4363.02 | D33: 4363.02 | E33: 0 | F33: 0 | G33: 0 | H33: 0 | I33: 0 | J33: 0 | K33: 0 | L33: 0 | M33: 0 | N33: 0 | O33: 0 | P33: 0 | Q33: 0 | R33: 0 | S33: 0 | T33: =SUM(D33:S33) | U33: =B33-T33
A34: Chinchi Mano de Obra y Materiales (eléctrico) Bod 150m | B34: 2327.19 | D34: 0 | E34: 2327.19 | F34: 0 | G34: 0 | H34: 0 | I34: 0 | J34: 0 | K34: 0 | L34: 0 | M34: 0 | N34: 0 | O34: 0 | P34: 0 | Q34: 0 | R34: 0 | S34: 0 | T34: =SUM(D34:S34) | U34: =B34-T34
A35: Transporte de Container | B35: 198 | D35: 198 | E35: 0 | F35: 0 | G35: 0 | H35: 0 | I35: 0 | J35: 0 | K35: 0 | L35: 0 | M35: 0 | N35: 0 | O35: 0 | P35: 0 | Q35: 0 | R35: 0 | S35: 0 | T35: =SUM(D35:S35) | U35: =B35-T35
A36: Flores (Mano de obra Const. Compatty 680m2) | B36: =10258+4160.13 | D36: 0 | E36: 0 | F36: =+B36/4 | G36: =+F36 | H36: =+G36 | I36: =+H36 | J36: 0 | K36: 0 | L36: 0 | M36: 0 | N36: 0 | O36: 0 | P36: 0 | Q36: 0 | R36: 0 | S36: 0 | T36: =SUM(D36:S36) | U36: =B36-T36
A37: Flores (Materiales Const. Compatty 680m2) | B37: =12166.54+8860.75 | D37: 0 | E37: 0 | F37: =+B37/4 | G37: =+F37 | H37: =+G37 | I37: =+H37 | J37: 0 | K37: 0 | L37: 0 | M37: 0 | N37: 0 | O37: 0 | P37: 0 | Q37: 0 | R37: 0 | S37: 0 | T37: =SUM(D37:S37) | U37: =B37-T37
A38: Flores (Mano de obra Enblocado y Enlucido de Paso Vial) | B38: 3450 | D38: 0 | E38: =+B38*30% | F38: 0 | G38: 0 | H38: =+B38*40% | I38: 0 | J38: 0 | K38: =+B38*30% | L38: 0 | M38: 0 | N38: 0 | O38: 0 | P38: 0 | Q38: 0 | R38: 0 | S38: 0 | T38: =SUM(D38:S38) | U38: =B38-T38
A39: Flores (MaterialesEnblocado y Enlucido de Paso Vial) | B39: 2643.85 | D39: 0 | E39: 0 | F39: 0 | G39: 0 | H39: 0 | I39: 0 | J39: 0 | K39: 0 | L39: 0 | M39: 0 | N39: 0 | O39: 0 | P39: 0 | Q39: 0 | R39: 0 | S39: 0 | T39: =SUM(D39:S39) | U39: =B39-T39
A40: Estructura Metalica - Sra Ruth Mano de Obra - Bod.680m2 Compatty | B40: 6500 | D40: 0 | E40: 928.57143 | F40: 928.57143 | G40: 928.57143 | H40: 928.57143 | I40: 928.57143 | J40: 928.57143 | K40: 928.57143 | L40: 0 | M40: 0 | N40: 0 | O40: 0 | P40: 0 | Q40: 0 | R40: 0 | S40: 0 | T40: =SUM(D40:S40) | U40: =B40-T40
A41: Estructura Metalica - Sra Ruth Materiales Obra - Bod.680m2 Compatty | B41: 12000 | D41: 0 | E41: 0 | F41: 0 | G41: 0 | H41: 4450.18 | I41: 0 | J41: 0 | K41: 7549.82 | L41: 0 | M41: 0 | N41: 0 | O41: 0 | P41: 0 | Q41: 0 | R41: 0 | S41: 0 | T41: =SUM(D41:S41) | U41: =B41-T41
A42: Adoquinado — mano de obra | B42: =PARAMETROS!$B$35 | D42: 0 | E42: 0 | F42: 0 | G42: 0 | H42: 0 | I42: 0 | J42: 0 | K42: 0 | L42: 0 | M42: 0 | N42: 0 | O42: 0 | P42: 0 | Q42: 0 | R42: 0 | S42: 0 | T42: =SUM(D42:S42) | U42: =B42-T42
A43: Adoquinado — material | B43: =PARAMETROS!$B$36 | D43: 0 | E43: 0 | F43: 0 | G43: 0 | H43: 0 | I43: 0 | J43: 0 | K43: 0 | L43: 0 | M43: 0 | N43: 0 | O43: 0 | P43: 0 | Q43: 0 | R43: 0 | S43: 0 | T43: =SUM(D43:S43) | U43: =B43-T43
A44: Materiales - Dipac | B44: 2485.14 | D44: 2485.14 | E44: 0 | F44: 0 | G44: 0 | H44: 0 | I44: 0 | J44: 0 | K44: 0 | L44: 0 | M44: 0 | N44: 0 | O44: 0 | P44: 0 | Q44: 0 | R44: 0 | S44: 0 | T44: =SUM(D44:S44) | U44: =B44-T44
A45: Materiales Internegocios - Fact # 20542 | B45: 45.59 | D45: 0 | E45: 0 | F45: 0 | G45: 45.59 | H45: 0 | I45: 0 | J45: 0 | K45: 0 | L45: 0 | M45: 0 | N45: 0 | O45: 0 | P45: 0 | Q45: 0 | R45: 0 | S45: 0 | T45: =SUM(D45:S45) | U45: =B45-T45
A46: Materiales Internegocios - Fact # 20514 | B46: 520.46 | D46: 0 | E46: 0 | F46: 0 | G46: 520.46 | H46: 0 | I46: 0 | J46: 0 | K46: 0 | L46: 0 | M46: 0 | N46: 0 | O46: 0 | P46: 0 | Q46: 0 | R46: 0 | S46: 0 | T46: =SUM(D46:S46) | U46: =B46-T46
A47: Materiales Internegocios - Fact # 20485 | B47: 1253.11 | D47: 0 | E47: 0 | F47: 0 | G47: 1253.11 | H47: 0 | I47: 0 | J47: 0 | K47: 0 | L47: 0 | M47: 0 | N47: 0 | O47: 0 | P47: 0 | Q47: 0 | R47: 0 | S47: 0 | T47: =SUM(D47:S47) | U47: =B47-T47
A48: Proyección 8 Bod 150m2 (21 -28) | D48: 0 | E48: 0 | F48: 0 | G48: 0 | H48: 0 | I48: 0 | J48: 0 | K48: 0 | L48: 0 | M48: 0 | N48: 0 | O48: 0 | P48: 0 | Q48: 0 | R48: 0 | S48: 0 | T48: =SUM(D48:S48) | U48: =B48-T48
A49: 10 Viajes de arena | B49: =10*80 | D49: 0 | E49: 800 | F49: 0 | G49: 0 | H49: 0 | I49: 0 | J49: 0 | K49: 0 | L49: 0 | M49: 0 | N49: 0 | O49: 0 | P49: 0 | Q49: 0 | R49: 0 | S49: 0 | T49: =SUM(D49:S49) | U49: =B49-T49
A50: (nuevo rubro de obra — escriba el nombre y el monto en TOTAL/META) | B50: 0 | D50: 0 | E50: 0 | F50: 0 | G50: 0 | H50: 0 | I50: 0 | J50: 0 | K50: 0 | L50: 0 | M50: 0 | N50: 0 | O50: 0 | P50: 0 | Q50: 0 | R50: 0 | S50: 0 | T50: =SUM(D50:S50) | U50: =B50-T50
A51: SUBTOTAL EGRESOS DE OBRA | B51: =SUM(B23:B50) | D51: =SUM(D23:D50) | E51: =SUM(E23:E50) | F51: =SUM(F23:F50) | G51: =SUM(G23:G50) | H51: =SUM(H23:H50) | I51: =SUM(I23:I50) | J51: =SUM(J23:J50) | K51: =SUM(K23:K50) | ... U51: =SUM(U23:U50)
A53: TOTAL EGRESOS (fijos + obra) | D53: =D21+D51 | E53: =E21+E51 | F53: =F21+F51 | G53: =G21+G51 | H53: =H21+H51 | I53: =I21+I51 | J53: =J21+J51 | K53: =K21+K51 | ... S53: =S21+S51
A54: FLUJO NETO DE LA SEMANA | D54: =D11-D53 | E54: =E11-E53 | F54: =F11-F53 | G54: =G11-G53 | H54: =H11-H53 | I54: =I11-I53 | J54: =J11-J53 | K54: =K11-K53 | ... S54: =S11-S53
A55: SALDO FINAL DE CAJA | D55: =D6+D54 | E55: =E6+E54 | F55: =F6+F54 | G55: =G6+G54 | H55: =H6+H54 | I55: =I6+I54 | J55: =J6+J54 | K55: =K6+K54 | ... S55: =S6+S54
A57: Caja mínima de seguridad (referencia) | D57: =PARAMETROS!$B$28 | E57: =PARAMETROS!$B$28 | F57: =PARAMETROS!$B$28 | G57: =PARAMETROS!$B$28 | H57: =PARAMETROS!$B$28 | I57: =PARAMETROS!$B$28 | J57: =PARAMETROS!$B$28 | K57: =PARAMETROS!$B$28 | ... S57: =PARAMETROS!$B$28
A58: Colchón sobre el mínimo (saldo final − mínimo) | D58: =D55-D57 | E58: =E55-E57 | F58: =F55-F57 | G58: =G55-G57 | H58: =H55-H57 | I58: =I55-I57 | J58: =J55-J57 | K58: =K55-K57 | ... S58: =S55-S57
A59: ESTADO DE LA SEMANA | D59: =IF(D55<0,"🔴 NEGATIVO",IF(D55<D57,"🟠 ALERTA","🟢 OK")) | E59: =IF(E55<0,"🔴 NEGATIVO",IF(E55<E57,"🟠 ALERTA","🟢 OK")) | F59: =IF(F55<0,"🔴 NEGATIVO",IF(F55<F57,"🟠 ALERTA","🟢 OK")) | G59: =IF(G55<0,"🔴 NEGATIVO",IF(G55<G57,"🟠 ALERTA","🟢 OK")) | H59: =IF(H55<0,"🔴 NEGATIVO",IF(H55<H57,"🟠 ALERTA","🟢 OK")) | I59: =IF(I55<0,"🔴 NEGATIVO",IF(I55<I57,"🟠 ALERTA","🟢 OK")) | J59: =IF(J55<0,"🔴 NEGATIVO",IF(J55<J57,"🟠 ALERTA","🟢 OK")) | K59: =IF(K55<0,"🔴 NEGATIVO",IF(K55<K57,"🟠 ALERTA","🟢 OK")) | ... S59: =IF(S55<0,"🔴 NEGATIVO",IF(S55<S57,"🟠 ALERTA","🟢 OK"))
A61: DÉFICIT PROYECTADO — mirando 1 semana adelante (plazo Agroaéreo) | D61: =MIN(0,E55-E57) | E61: =MIN(0,F55-F57) | F61: =MIN(0,G55-G57) | G61: =MIN(0,H55-H57) | H61: =MIN(0,I55-I57) | I61: =MIN(0,J55-J57) | J61: =MIN(0,K55-K57) | K61: =MIN(0,L55-L57) | ... R61: =MIN(0,S55-S57) | S61: —
A62: ➤ ACCIÓN: SOLICITAR A AGROAÉREO ESTA SEMANA | D62: =IF(D61<0,"Pedir "&TEXT(-D61,"$#,#0")&" ahora para SEM 38","No se requiere") | E62: =IF(E61<0,"Pedir "&TEXT(-E61,"$#,#0")&" ahora para SEM 39","No se requiere") | F62: =IF(F61<0,"Pedir "&TEXT(-F61,"$#,#0")&" ahora para SEM 39","No se requiere") | G62: =IF(G61<0,"Pedir "&TEXT(-G61,"$#,#0")&" ahora para SEM 41","No se requiere") | H62: =IF(H61<0,"Pedir "&TEXT(-H61,"$#,#0")&" ahora para SEM 42","No se requiere") | I62: =IF(I61<0,"Pedir "&TEXT(-I61,"$#,#0")&" ahora para SEM 43","No se requiere") | J62: =IF(J61<0,"Pedir "&TEXT(-J61,"$#,#0")&" ahora para SEM 44","No se requiere") | K62: =IF(K61<0,"Pedir "&TEXT(-K61,"$#,#0")&" ahora para SEM 45","No se requiere") | L62: =IF(L61<0,"Pedir "&TEXT(-L61,"$#,#0")&" ahora para SEM 46","No se requiere") | M62: =IF(M61<0,"Pedir "&TEXT(-M61,"$#,#0")&" ahora para SEM 47","No se requiere") | N62: =IF(N61<0,"Pedir "&TEXT(-N61,"$#,#0")&" ahora para SEM 48","No se requiere") | O62: =IF(O61<0,"Pedir "&TEXT(-O61,"$#,#0")&" ahora para SEM 49","No se requiere") | P62: =IF(P61<0,"Pedir "&TEXT(-P61,"$#,#0")&" ahora para SEM 50","No se requiere") | Q62: =IF(Q61<0,"Pedir "&TEXT(-Q61,"$#,#0")&" ahora para SEM 51","No se requiere") | R62: =IF(R61<0,"Pedir "&TEXT(-R61,"$#,#0")&" ahora para SEM 52","No se requiere") | S62: =IF(S61<0,"Pedir "&TEXT(-S61,"$#,#0")&" ahora para SEM 52","No se requiere")
D67: =(+B30+B31+B34+B29+B32)*8

Sheet Estadística
B3: =+'FLUJO SEMANAL'!A4 | C3: =+'FLUJO SEMANAL'!D5 | D3: =+'FLUJO SEMANAL'!E5 | E3: =+'FLUJO SEMANAL'!F5 | F3: =+'FLUJO SEMANAL'!G5 | G3: =+'FLUJO SEMANAL'!H5 | H3: =+'FLUJO SEMANAL'!I5 | I3: =+'FLUJO SEMANAL'!J5 | J3: =+'FLUJO SEMANAL'!K5 | ... L3: =+'FLUJO SEMANAL'!M5
B4: =+'FLUJO SEMANAL'!A11 | C4: =+'FLUJO SEMANAL'!D6 | D4: =+'FLUJO SEMANAL'!E6 | E4: =+'FLUJO SEMANAL'!F6 | F4: =+'FLUJO SEMANAL'!G6 | G4: =+'FLUJO SEMANAL'!H6 | H4: =+'FLUJO SEMANAL'!I6 | I4: =+'FLUJO SEMANAL'!J6 | J4: =+'FLUJO SEMANAL'!K6 | ... L4: =+'FLUJO SEMANAL'!M6
B5: =+'FLUJO SEMANAL'!A53 | C5: =+'FLUJO SEMANAL'!D53 | D5: =+'FLUJO SEMANAL'!E53 | E5: =+'FLUJO SEMANAL'!F53 | F5: =+'FLUJO SEMANAL'!G53 | G5: =+'FLUJO SEMANAL'!H53 | H5: =+'FLUJO SEMANAL'!I53 | I5: =+'FLUJO SEMANAL'!J53 | J5: =+'FLUJO SEMANAL'!K53 | ... L5: =+'FLUJO SEMANAL'!M53
B6: =+'FLUJO SEMANAL'!A55 | C6: =+'FLUJO SEMANAL'!D55 | D6: =+'FLUJO SEMANAL'!E55 | E6: =+'FLUJO SEMANAL'!F55 | F6: =+'FLUJO SEMANAL'!G55 | G6: =+'FLUJO SEMANAL'!H55 | H6: =+'FLUJO SEMANAL'!I55 | I6: =+'FLUJO SEMANAL'!J55 | J6: =+'FLUJO SEMANAL'!K55 | ... L6: =+'FLUJO SEMANAL'!M55

Sheet RESUMEN Y ALERTA
A1: RESUMEN GERENCIAL Y ALERTA DE FONDEO — AL CORTE DE PARAMETROS
A2: Se recalcula solo cuando se actualiza PARAMETROS o FLUJO SEMANAL. Ver también la hoja INSTRUCTIVO CPA.
A4: 1. POSICIÓN DE CAJA
A5: Saldo real de caja al corte | B5: =PARAMETROS!B11
A6: Caja mínima de seguridad (1,5× gasto fijo mensual) | B6: =PARAMETROS!B28
A7: Colchón disponible sobre el mínimo, HOY | B7: =B5-B6
A8: Meses de gasto fijo que cubre la caja de hoy (objetivo > 2 meses) | B8: =PARAMETROS!B11/PARAMETROS!B25
A10: 2. GENERACIÓN OPERATIVA Y CUPO DE INVERSIÓN SOSTENIBLE
A11: Ingreso operativo semanal | B11: =PARAMETROS!C15
A12: (–) Subtotal egresos fijos semanales (todas las categorías) | B12: =-PARAMETROS!C25
A13: GENERACIÓN OPERATIVA NETA SEMANAL (cupo sostenible sin financiamiento externo) | B13: =B11+B12
A14: Ritmo histórico de gasto en obra (jul-ago 2026, referencia) | B14: 10088.13
A15: Veces que el ritmo de obra excede el cupo sostenible | B15: =B14/B13
A17: 3. NECESIDAD DE FONDEO PROYECTADA — SEM 37 A SEM 52
A18: Acción inmediata — pedir esta semana (SEM 37) para cubrir SEM 38 | B18: =-MIN(0,'FLUJO SEMANAL (2)'!D76)
A19: Punto de mayor déficit en todo el horizonte SI NO llega financiamiento (peor caso, no acumulativo) | B19: =-MIN(0,MIN('FLUJO SEMANAL (2)'!D76:AI76))
A20: 🚦 Cada déficit ya incluye el que le precede si no se resuelve — no sume las filas de esta sección, cada una es independiente sobre el escenario de no recibir fondeo.
A21: Número de semanas en que hace falta solicitar fondeo | B21: =COUNTIF('FLUJO SEMANAL (2)'!D76:AI76,"<0")
A22: Total obra pendiente por programar (todos los rubros) | B22: =PARAMETROS!B39
A24: 4. QUÉ DICE ESTO
A25: El cupo de inversión sostenible (fila 2) es lo máximo que Mobijuesa puede poner en obra CADA
A26: SEMANA con caja propia, sin tocar el colchón de seguridad ni pedir financiamiento externo. Todo lo
A27: que la obra necesite por encima de ese número, semana a semana, es exactamente lo que la hoja
A28: FLUJO SEMANAL calcula en la fila 'ACCIÓN: SOLICITAR A AGROAÉREO ESTA SEMANA' — con una semana de
A29: anticipación mínima, porque el fondo tarda al menos 7 días en llegar.
A31: Lectura con la matriz de 4 bloques (Altimira): el bloque que se rompe es Cobertura, no Rentabilidad.
A32: El negocio sigue generando margen; lo que no alcanza es el RITMO al que la obra consume caja frente
A33: al ritmo al que la operación la repone. La solución no es vender más rápido — es que el financiamiento
A34: de Agroaéreo llegue ANTES de que la obra lo necesite, no después.
A36: Regla operativa para el equipo: revisar esta hoja cada lunes. Si la fila 3 (necesidad de fondeo)
A37: sube de una semana a otra sin que haya llegado un aporte de Agroaéreo, es señal de que el ritmo de
A38: obra se está acelerando por encima de lo planificado — frenar antes de comprometer más pagos.

Sheet FLUJO SEMANAL (2)
A1: FLUJO DE CAJA SEMANAL — SEM 37 A SEM 52 DE 2026 y 2027
A2: Fórmulas vivas: edite PARAMETROS para cambiar supuestos, o escriba un valor real directo en una celda de semana para reemplazar el estimado.
A4: CONCEPTO | B4: TOTAL / META | C4: SALDO INICIAL | D4: SEM 37 | E4: SEM 38 | F4: SEM 39 | G4: SEM 40 | H4: SEM 41 | I4: SEM 42 | J4: SEM 43 | K4: SEM 44 | L4: SEM 45 | M4: SEM 46 | N4: SEM 47 | O4: SEM 48 | P4: SEM 49 | Q4: SEM 50 | R4: SEM 51 | S4: SEM 52 | T4: SEM 1 | U4: SEM 2 | V4: SEM 3 | W4: SEM 4 | X4: SEM 5 | Y4: SEM 6 | Z4: SEM 7 | AA4: SEM 8 | AB4: SEM 9 | AC4: SEM 10 | AD4: SEM 11 | AE4: SEM 12 | AF4: SEM 13 | AG4: SEM 14 | AH4: SEM 15 | AI4: SEM 16 | AJ4: TOTAL PROGR. | AK4: DIFEREN- CIA
A5: Semana del … al … (calendario) | D5: 07-Sep / 13-Sep | E5: 14-Sep / 20-Sep | F5: 21-Sep / 27-Sep | G5: oct | H5: oct | I5: oct | J5: oct | K5: nov | L5: nov | M5: nov | N5: nov | O5: nov | P5: dic | Q5: dic | R5: dic | S5: dic | T5: ene | U5: ene | V5: ene | W5: ene | X5: feb | Y5: feb | Z5: feb | AA5: feb | AB5: mar | AC5: mar | AD5: mar | AE5: mar | AF5: abr | AG5: abr | AH5: abr | AI5: abr
A6: SALDO INICIAL DE CAJA | D6: =PARAMETROS!$B$11 | E6: =D70 | F6: =E70 | G6: =F70 | H6: =G70 | I6: =H70 | J6: =I70 | K6: =J70 | L6: =K70 | ... AI6: =AH70
A7: INGRESOS
A8: Ingreso operativo estimado (clientes) | B8: ver PARAMETROS | D8: 24965.7 | E8: 22627.44 | F8: 14884.46 | G8: =PARAMETROS!$H$15 | H8: =PARAMETROS!$E$15 | I8: =PARAMETROS!$F$15 | J8: =PARAMETROS!$G$15 | K8: =PARAMETROS!$H$15 | L8: =PARAMETROS!$E$15 | M8: =PARAMETROS!$F$15 | N8: =PARAMETROS!$G$15 | O8: =PARAMETROS!$H$15 | P8: =PARAMETROS!$E$15 | Q8: =PARAMETROS!$F$15 | R8: =PARAMETROS!$G$15 | S8: =PARAMETROS!$H$15 | T8: =PARAMETROS!$E$15 | U8: =PARAMETROS!$F$15 | V8: =PARAMETROS!$G$15 | W8: =PARAMETROS!$H$15 | X8: =PARAMETROS!$E$15 | Y8: =PARAMETROS!$F$15 | Z8: =PARAMETROS!$G$15 | AA8: =PARAMETROS!$H$15 | AB8: =PARAMETROS!$E$15 | AC8: =PARAMETROS!$F$15 | AD8: =PARAMETROS!$G$15 | AE8: =PARAMETROS!$H$15 | AF8: =PARAMETROS!$E$15 | AG8: =PARAMETROS!$F$15 | AH8: =PARAMETROS!$G$15 | AI8: =PARAMETROS!$H$15 | AJ8: =SUM(D8:AI8)
A9: Aportes recibidos de Agroaéreo | C9: 30000 | D9: 0 | E9: 0 | F9: 0 | G9: 0 | H9: 30000 | I9: 0 | J9: 0 | K9: 0 | L9: 0 | M9: 0 | N9: 0 | O9: 0 | P9: 30000 | Q9: 0 | R9: 0 | S9: 0 | T9: 0 | U9: 0 | V9: 0 | W9: 0 | X9: 30000 | Y9: 0 | Z9: 0 | AA9: 0 | AB9: 0 | AC9: 0 | AD9: 0 | AE9: 0 | AF9: 0 | AG9: 0 | AH9: 0 | AI9: 0 | AJ9: =SUM(C9:AI9)
A10: Otros ingresos (ventas, reembolsos, etc.) | D10: 0 | E10: 0 | F10: 0 | G10: 0 | H10: 0 | I10: 0 | J10: 0 | K10: 0 | L10: 0 | M10: 0 | N10: 0 | O10: 0 | P10: 0 | Q10: 0 | R10: 0 | S10: 0 | T10: 0 | U10: =420*4+900*4-900-270 | V10: 0 | W10: 0 | X10: 0 | Y10: 0 | Z10: =+U10 | AA10: 0 | AB10: 0 | AC10: 0 | AD10: =+Z10 | AE10: 0 | AF10: 0 | AG10: =+AD10 | AH10: 0 | AI10: 0 | AJ10: =SUM(D10:AI10)
A11: TOTAL INGRESOS | D11: =SUM(D8:D10) | E11: =SUM(E8:E10) | F11: =SUM(F8:F10) | G11: =SUM(G8:G10) | H11: =SUM(H8:H10) | I11: =SUM(I8:I10) | J11: =SUM(J8:J10) | K11: =SUM(K8:K10) | ... AI11: =SUM(AI8:AI10) | AJ11: =SUM(D11:AI11)
A12: EGRESOS FIJOS (operativos, administrativos, legales)
A13: Gasto operativo y administrativo | D13: 0 | E13: 0 | F13: 0 | G13: =1555+100+100 | H13: 0 | I13: 0 | J13: 0 | K13: =1555+100+100 | L13: 0 | M13: 0 | N13: 0 | O13: =1555+100+100 | P13: 0 | Q13: 0 | R13: 0 | S13: =1555+100+100 | T13: 0 | U13: 0 | V13: 0 | W13: =1555+100+100 | X13: 0 | Y13: 0 | Z13: 0 | AA13: =1555+100+100 | AB13: 0 | AC13: 0 | AD13: 0 | AE13: =1555+100+100 | AF13: 0 | AG13: 0 | AH13: 0 | AI13: =1555+100+100
A14: Mantenimiento de bodegas en operación | B14: 45.59 | D14: 0 | E14: =462.31+164.26 | F14: 0 | G14: 0 | H14: 45.59 | I14: 0 | J14: 0 | K14: 0 | L14: 0 | M14: 0 | N14: 0 | O14: 0 | P14: 0 | Q14: 0 | R14: 0 | S14: 0 | T14: 0 | U14: 0 | V14: 0 | W14: 0 | X14: 0 | Y14: 0 | Z14: 0 | AA14: 0 | AB14: 0 | AC14: 0 | AD14: 0 | AE14: 0 | AF14: 0 | AG14: 0 | AH14: 0 | AI14: 0
A15: Impuestos, prediales y gastos bancarios | D15: 0 | E15: 0 | F15: 0 | G15: 0 | H15: 0 | I15: 0 | J15: 0 | K15: 0 | L15: 0 | M15: 0 | N15: 0 | O15: 0 | P15: 0 | Q15: 0 | R15: 0 | S15: 0 | T15: 0 | U15: 0 | V15: 0 | W15: 0 | X15: 0 | Y15: 0 | Z15: 0 | AA15: 0 | AB15: 0 | AC15: 0 | AD15: 0 | AE15: 0 | AF15: 0 | AG15: 0 | AH15: 0 | AI15: 0
A16: Servicio de deuda — Cooperativa La Nuestra | D16: 0 | E16: 1094 | F16: 0 | G16: 0 | H16: 0 | I16: 1045 | J16: 0 | K16: 0 | L16: 0 | M16: 1045 | N16: 0 | O16: 0 | P16: 0 | Q16: 1045 | R16: 0 | S16: 0 | T16: 0 | U16: 1045 | V16: 0 | W16: 0 | X16: 0 | Y16: 1045 | Z16: 0 | AA16: 0 | AB16: 0 | AC16: 1045 | AD16: 0 | AE16: 0 | AF16: 0 | AG16: 1045 | AH16: 0 | AI16: 0
A17: Estudios, planos y levantamientos | D17: 0 | E17: 0 | F17: 0 | G17: 0 | H17: 0 | I17: 0 | J17: 0 | K17: 0 | L17: 0 | M17: 0 | N17: 0 | O17: 0 | P17: 0 | Q17: 0 | R17: 0 | S17: 0 | T17: 0 | U17: 0 | V17: 0 | W17: 0 | X17: 0 | Y17: 0 | Z17: 0 | AA17: 0 | AB17: 0 | AC17: 0 | AD17: 0 | AE17: 0 | AF17: 0 | AG17: 0 | AH17: 0 | AI17: 0
A18: Retiros de socios / gasto societario y legal (normalizado) | D18: 0 | E18: 0 | F18: 0 | G18: 0 | H18: 0 | I18: 0 | J18: 0 | K18: 0 | L18: 0 | M18: 0 | N18: 0 | O18: 0 | P18: 0 | Q18: 0 | R18: 0 | S18: 0 | T18: 0 | U18: 0 | V18: 0 | W18: 0 | X18: 0 | Y18: 0 | Z18: 0 | AA18: 0 | AB18: 0 | AC18: 0 | AD18: 0 | AE18: 0 | AF18: 0 | AG18: 0 | AH18: 0 | AI18: 0
A19: Alicuotas | D19: 624.59 | E19: 0 | F19: 0 | G19: 0 | H19: 624.59 | I19: 0 | J19: 0 | K19: 0 | L19: 624.59 | M19: 0 | N19: 0 | O19: 0 | P19: 624.59 | Q19: 0 | R19: 0 | S19: 0 | T19: 624.59 | U19: 0 | V19: 0 | W19: 0 | X19: 624.59 | Y19: 0 | Z19: 0 | AA19: 0 | AB19: 624.59 | AC19: 0 | AD19: 0 | AE19: 0 | AF19: 624.59 | AG19: 0 | AH19: 0 | AI19: 0
A20: Consumo de Energia Electrica | D20: 125.88 | E20: 16.05 | F20: 0 | G20: 0 | H20: 0 | I20: 0 | J20: 0 | K20: 0 | L20: 0 | M20: 0 | N20: 0 | O20: 0 | P20: 0 | Q20: 0 | R20: 0 | S20: 0 | T20: 0 | U20: 0 | V20: 0 | W20: 0 | X20: 0 | Y20: 0 | Z20: 0 | AA20: 0 | AB20: 0 | AC20: 0 | AD20: 0 | AE20: 0 | AF20: 0 | AG20: 0 | AH20: 0 | AI20: 0
A21: SUBTOTAL EGRESOS FIJOS (costo unitario m2) | D21: =SUM(D13:D20) | E21: =SUM(E13:E20) | F21: =SUM(F13:F20) | G21: =SUM(G13:G20) | H21: =SUM(H13:H20) | I21: =SUM(I13:I20) | J21: =SUM(J13:J20) | K21: =SUM(K13:K20) | ... AI21: =SUM(AI13:AI20)
A22: EGRESOS DE OBRA / CONSTRUCCIÓN — valores sugeridos al ritmo de $10.000/sem; reprograme según pagos reales
A23: Tapia (Mano de Obra estructura 1300mtrs) Bod. 16-17 | B23: 24440 | C23: 21656 | D23: 2050.8 | E23: 0 | F23: 0 | G23: 0 | H23: 0 | I23: 0 | J23: 0 | K23: 0 | L23: 0 | M23: 0 | N23: 0 | O23: 0 | P23: 0 | Q23: 0 | R23: 0 | S23: 0 | T23: 0 | U23: 0 | V23: 0 | W23: 0 | X23: 0 | Y23: 0 | Z23: 0 | AA23: 0 | AB23: 0 | AC23: 0 | AD23: 0 | AE23: 0 | AF23: 0 | AG23: 0 | AH23: 0 | AI23: 0 | AJ23: =SUM(C23:AI23) | AK23: =B23-AJ23
A24: Tapia (Materiales estructura 1300mtrs) Bod. 16-17 | B24: 38379.2 | C24: 38379.2 | D24: 0 | E24: 0 | F24: 0 | G24: 0 | H24: 0 | I24: 0 | J24: 0 | K24: 0 | L24: 0 | M24: 0 | N24: 0 | O24: 0 | P24: 0 | Q24: 0 | R24: 0 | S24: 0 | T24: 0 | U24: 0 | V24: 0 | W24: 0 | X24: 0 | Y24: 0 | Z24: 0 | AA24: 0 | AB24: 0 | AC24: 0 | AD24: 0 | AE24: 0 | AF24: 0 | AG24: 0 | AH24: 0 | AI24: 0 | AJ24: =SUM(C24:AI24) | AK24: =B24-AJ24
A25: Tapia (Mano de Obra y materiales 5 puertas corredizas) bod 1300m2 | B25: 9000 | C25: 0 | D25: 2000 | E25: 3000 | F25: 1000 | G25: 1000 | H25: 1000 | I25: 1000 | J25: 1000 | K25: 1000 | L25: 0 | M25: 0 | N25: 0 | O25: 0 | P25: 0 | Q25: 0 | R25: 0 | S25: 0 | T25: 0 | U25: 0 | V25: 0 | W25: 0 | X25: 0 | Y25: 0 | Z25: 0 | AA25: 0 | AB25: 0 | AC25: 0 | AD25: 0 | AE25: 0 | AF25: 0 | AG25: 0 | AH25: 0 | AI25: 0 | AJ25: =SUM(C25:AI25) | AK25: =B25-AJ25
A26: Tapia (Mano de Obra pared metalica) bod 1300m2 | B26: 4416 | C26: 0 | D26: 0 | E26: 1324.8 | F26: 2000 | G26: 1324.8 | H26: 0 | I26: 0 | J26: 0 | K26: 0 | L26: 0 | M26: 0 | N26: 0 | O26: 0 | P26: 0 | Q26: 0 | R26: 0 | S26: 0 | T26: 0 | U26: 0 | V26: 0 | W26: 0 | X26: 0 | Y26: 0 | Z26: 0 | AA26: 0 | AB26: 0 | AC26: 0 | AD26: 0 | AE26: 0 | AF26: 0 | AG26: 0 | AH26: 0 | AI26: 0 | AJ26: =SUM(C26:AI26) | AK26: =B26-AJ26
A27: Tapia (Materiales pared metalica) | B27: =2485.014+777.95+47.78 | C27: 0 | D27: 2485.14 | E27: 0 | F27: 597.14 | G27: 0 | H27: 47.78 | I27: 764.42 | J27: 0 | K27: 0 | L27: 0 | M27: 0 | N27: 0 | O27: 0 | P27: 0 | Q27: 0 | R27: 0 | S27: 0 | T27: 0 | U27: 0 | V27: 0 | W27: 0 | X27: 0 | Y27: 0 | Z27: 0 | AA27: 0 | AB27: 0 | AC27: 0 | AD27: 0 | AE27: 0 | AF27: 0 | AG27: 0 | AH27: 0 | AI27: 0 | AJ27: =SUM(C27:AI27) | AK27: =B27-AJ27
A28: Flores (Mano de Obra cimentación) Bod. 16-17 bod 1300m2 | B28: 15346.8 | C28: 13993.9 | D28: 1352.43 | E28: 0 | F28: 0 | G28: 0 | H28: 0 | I28: 0 | J28: 0 | K28: 0 | L28: 0 | M28: 0 | N28: 0 | O28: 0 | P28: 0 | Q28: 0 | R28: 0 | S28: 0 | T28: 0 | U28: 0 | V28: 0 | W28: 0 | X28: 0 | Y28: 0 | Z28: 0 | AA28: 0 | AB28: 0 | AC28: 0 | AD28: 0 | AE28: 0 | AF28: 0 | AG28: 0 | AH28: 0 | AI28: 0 | AJ28: =SUM(C28:AI28) | AK28: =B28-AJ28
A29: Flores (Materiales cimentación) Bod. 16-17 bod 1300m2 | B29: 26406.9 | C29: 26406.9 | D29: 0 | E29: 0 | F29: 0 | G29: 0 | H29: 0 | I29: 0 | J29: 0 | K29: 0 | L29: 0 | M29: 0 | N29: 0 | O29: 0 | P29: 0 | Q29: 0 | R29: 0 | S29: 0 | T29: 0 | U29: 0 | V29: 0 | W29: 0 | X29: 0 | Y29: 0 | Z29: 0 | AA29: 0 | AB29: 0 | AC29: 0 | AD29: 0 | AE29: 0 | AF29: 0 | AG29: 0 | AH29: 0 | AI29: 0 | AJ29: =SUM(C29:AI29) | AK29: =B29-AJ29
A30: Flores (Mano de Obra piso, emblocado) bod 1300m2 | B30: 13788.77 | C30: 4136.63 | D30: 0 | E30: 5515.51 | F30: 0 | G30: 4136.63 | H30: 0 | I30: 0 | J30: 1197.89 | K30: 0 | L30: 0 | M30: 0 | N30: 0 | O30: 0 | P30: 0 | Q30: 0 | R30: 0 | S30: 0 | T30: 0 | U30: 0 | V30: 0 | W30: 0 | X30: 0 | Y30: 0 | Z30: 0 | AA30: 0 | AB30: 0 | AC30: 0 | AD30: 0 | AE30: 0 | AF30: 0 | AG30: 0 | AH30: 0 | AI30: 0 | AJ30: =SUM(C30:AI30) | AK30: =B30-AJ30
A31: Flores (Materiales piso, terminado) bod 1300m2 | B31: =3114.96/4*3 | C31: 0 | D31: 0 | E31: 0 | F31: 0 | G31: 0 | H31: 2336.22 | I31: 0 | J31: 0 | K31: 0 | L31: 0 | M31: 0 | N31: 0 | O31: 0 | P31: 0 | Q31: 0 | R31: 0 | S31: 0 | T31: 0 | U31: 0 | V31: 0 | W31: 0 | X31: 0 | Y31: 0 | Z31: 0 | AA31: 0 | AB31: 0 | AC31: 0 | AD31: 0 | AE31: 0 | AF31: 0 | AG31: 0 | AH31: 0 | AI31: 0 | AJ31: =SUM(C31:AI31) | AK31: =B31-AJ31
A32: Flores (Mano de Obra pozo septico) bod 1300m2 | B32: 1522.5 | C32: 761.25 | D32: 0 | E32: 0 | F32: 0 | G32: 0 | H32: 0 | I32: 0 | J32: 0 | K32: 0 | L32: 0 | M32: 0 | N32: 0 | O32: 0 | P32: 0 | Q32: 0 | R32: 0 | S32: 0 | T32: 0 | U32: 0 | V32: 0 | W32: 0 | X32: 0 | Y32: 0 | Z32: 0 | AA32: 0 | AB32: 0 | AC32: 0 | AD32: 0 | AE32: 0 | AF32: 0 | AG32: 0 | AH32: 0 | AI32: 0 | AJ32: =SUM(C32:AI32) | AK32: =B32-AJ32
A33: Flores (Materiales pozo septico) bod 1300m2 | B33: 1773.57 | C33: 0 | D33: 0 | E33: 0 | F33: 0 | G33: =520.46+1253.11 | H33: 0 | I33: 0 | J33: 0 | K33: 0 | L33: 0 | M33: 0 | N33: 0 | O33: 0 | P33: 0 | Q33: 0 | R33: 0 | S33: 0 | T33: 0 | U33: 0 | V33: 0 | W33: 0 | X33: 0 | Y33: 0 | Z33: 0 | AA33: 0 | AB33: 0 | AC33: 0 | AD33: 0 | AE33: 0 | AF33: 0 | AG33: 0 | AH33: 0 | AI33: 0 | AJ33: =SUM(C33:AI33) | AK33: =B33-AJ33
A34: Chinchi Mano de Obra y Materiales Bodegas 1300mtrs | B34: 5938.33 | C34: 5938.33 | D34: 0 | E34: 0 | F34: =1861.75+618.41 | G34: 0 | H34: 0 | I34: 0 | J34: 0 | K34: 0 | L34: 0 | M34: 0 | N34: 0 | O34: 0 | P34: 0 | Q34: 0 | R34: 0 | S34: 0 | T34: 0 | U34: 0 | V34: 0 | W34: 0 | X34: 0 | Y34: 0 | Z34: 0 | AA34: 0 | AB34: 0 | AC34: 0 | AD34: 0 | AE34: 0 | AF34: 0 | AG34: 0 | AH34: 0 | AI34: 0 | AJ34: =SUM(C34:AI34) | AK34: =B34-AJ34
A35: 10 Viajes de arena bod 1300m2 | B35: =10*80 | D35: 0 | E35: 0 | F35: 812 | G35: 0 | H35: 0 | I35: 0 | J35: 0 | K35: 0 | L35: 0 | M35: 0 | N35: 0 | O35: 0 | P35: 0 | Q35: 0 | R35: 0 | S35: 0 | T35: 0 | U35: 0 | V35: 0 | W35: 0 | X35: 0 | Y35: 0 | Z35: 0 | AA35: 0 | AB35: 0 | AC35: 0 | AD35: 0 | AE35: 0 | AF35: 0 | AG35: 0 | AH35: 0 | AI35: 0 | AJ35: =SUM(C35:AI35) | AK35: =B35-AJ35
A36: SUBTOTAL EGRESOS DE OBRA DE BODEGA 1300M2 | B36: =+SUM(B23:B35) | C36: =+SUM(B23:B35)/1300
A37: Flores (Mano de obra Const. Bodega 150m2) | B37: 2693.88 | D37: 0 | E37: 0 | F37: 0 | G37: 0 | H37: =+B37*40% | I37: 0 | J37: 0 | K37: =+B37*30% | L37: 0 | M37: 0 | N37: 0 | O37: 0 | P37: 0 | Q37: 0 | R37: 0 | S37: 0 | T37: 0 | U37: 0 | V37: 0 | W37: 0 | X37: 0 | Y37: 0 | Z37: 0 | AA37: 0 | AB37: 0 | AC37: 0 | AD37: 0 | AE37: 0 | AF37: 0 | AG37: 0 | AH37: 0 | AI37: 0 | AJ37: =SUM(C37:AI37) | AK37: =B37-AJ37
A38: Flores (Materiales Const. Bodega 150m2) | B38: 1507.31 | D38: 0 | E38: 0 | F38: 808.16 | G38: 0 | H38: 0 | I38: 442.44 | J38: 0 | K38: 0 | L38: 0 | M38: 0 | N38: 0 | O38: 0 | P38: 0 | Q38: 0 | R38: 0 | S38: 0 | T38: 0 | U38: 0 | V38: 0 | W38: 0 | X38: 0 | Y38: 0 | Z38: 0 | AA38: 0 | AB38: 0 | AC38: 0 | AD38: 0 | AE38: 0 | AF38: 0 | AG38: 0 | AH38: 0 | AI38: 0 | AJ38: =SUM(C38:AI38) | AK38: =B38-AJ38
A39: Flores (Materiales piso, terminado) bod 150m2 | B39: =3114.96/4 | D39: 0 | E39: 0 | F39: 0 | G39: 0 | H39: 778.74 | I39: 0 | J39: 0 | K39: 0 | L39: 0 | M39: 0 | N39: 0 | O39: 0 | P39: 0 | Q39: 0 | R39: 0 | S39: 0 | T39: 0 | U39: 0 | V39: 0 | W39: 0 | X39: 0 | Y39: 0 | Z39: 0 | AA39: 0 | AB39: 0 | AC39: 0 | AD39: 0 | AE39: 0 | AF39: 0 | AG39: 0 | AH39: 0 | AI39: 0 | AJ39: =SUM(C39:AI39) | AK39: =B39-AJ39
A40: Tapia (Mano de obra Const. Bodega 150m2 - Metálica) | B40: 1885 | D40: 0 | E40: 0 | F40: 0 | G40: 0 | H40: 0 | I40: 0 | J40: 0 | K40: 0 | L40: 0 | M40: 0 | N40: 0 | O40: 0 | P40: 0 | Q40: 0 | R40: 0 | S40: 0 | T40: 0 | U40: 0 | V40: 0 | W40: 0 | X40: 0 | Y40: 0 | Z40: 0 | AA40: 0 | AB40: 0 | AC40: 0 | AD40: 0 | AE40: 0 | AF40: 0 | AG40: 0 | AH40: 0 | AI40: 0 | AJ40: =SUM(C40:AI40) | AK40: =B40-AJ40
A41: Tapia (Materiales Const. Bodega 150m2 - Metálica) | B41: 2485.14 | D41: 0 | E41: 0 | F41: 0 | G41: 0 | H41: 0 | I41: 0 | J41: 0 | K41: 0 | L41: 0 | M41: 0 | N41: 0 | O41: 0 | P41: 0 | Q41: 0 | R41: 0 | S41: 0 | T41: 0 | U41: 0 | V41: 0 | W41: 0 | X41: 0 | Y41: 0 | Z41: 0 | AA41: 0 | AB41: 0 | AC41: 0 | AD41: 0 | AE41: 0 | AF41: 0 | AG41: 0 | AH41: 0 | AI41: 0 | AJ41: =SUM(C41:AI41) | AK41: =B41-AJ41
A42: Chinchi Mano de Obra y Materiales (eléctrico) Bod 150m | B42: 597.14 | D42: 0 | E42: 0 | F42: 0 | G42: 597.14 | H42: 0 | I42: 0 | J42: 0 | K42: 0 | L42: 0 | M42: 0 | N42: 0 | O42: 0 | P42: 0 | Q42: 0 | R42: 0 | S42: 0 | T42: 0 | U42: 0 | V42: 0 | W42: 0 | X42: 0 | Y42: 0 | Z42: 0 | AA42: 0 | AB42: 0 | AC42: 0 | AD42: 0 | AE42: 0 | AF42: 0 | AG42: 0 | AH42: 0 | AI42: 0 | AJ42: =SUM(C42:AI42) | AK42: =B42-AJ42
A43: Hormigon - Bodega 150m2 | B43: =4363.02+650 | D43: 4363.02 | E43: 650 | F43: 0 | G43: 0 | H43: 0 | I43: 0 | J43: 0 | K43: 0 | L43: 0 | M43: 0 | N43: 0 | O43: 0 | P43: 0 | Q43: 0 | R43: 0 | S43: 0 | T43: 0 | U43: 0 | V43: 0 | W43: 0 | X43: 0 | Y43: 0 | Z43: 0 | AA43: 0 | AB43: 0 | AC43: 0 | AD43: 0 | AE43: 0 | AF43: 0 | AG43: 0 | AH43: 0 | AI43: 0 | AJ43: =SUM(C43:AI43) | AK43: =B43-AJ43
A44: Transporte de Container - 150m2 | B44: 198 | D44: 198 | E44: 0 | F44: 0 | G44: 0 | H44: 0 | I44: 0 | J44: 0 | K44: 0 | L44: 0 | M44: 0 | N44: 0 | O44: 0 | P44: 0 | Q44: 0 | R44: 0 | S44: 0 | T44: 0 | U44: 0 | V44: 0 | W44: 0 | X44: 0 | Y44: 0 | Z44: 0 | AA44: 0 | AB44: 0 | AC44: 0 | AD44: 0 | AE44: 0 | AF44: 0 | AG44: 0 | AH44: 0 | AI44: 0 | AJ44: =SUM(C44:AI44) | AK44: =B44-AJ44
A45: Instalación Electrica Contenedores - bod 150m2 | B45: 156.19 | D45: 0 | E45: 156.19 | F45: 0 | G45: 0 | H45: 0 | I45: 0 | J45: 0 | K45: 0 | L45: 0 | M45: 0 | N45: 0 | O45: 0 | P45: 0 | Q45: 0 | R45: 0 | S45: 0 | T45: 0 | U45: 0 | V45: 0 | W45: 0 | X45: 0 | Y45: 0 | Z45: 0 | AA45: 0 | AB45: 0 | AC45: 0 | AD45: 0 | AE45: 0 | AF45: 0 | AG45: 0 | AH45: 0 | AI45: 0 | AJ45: =SUM(C45:AI45) | AK45: =B45-AJ45
A46: SUBTOTAL EGRESOS DE OBRA DE BODEGA 150 M2 | B46: =+SUM(B37:B45) | C46: =+SUM(B37:B45)/150
A47: Flores (Mano de obra Const. Compatty 680m2) | B47: =10258+4160.13 | D47: 0 | E47: 0 | F47: 0 | G47: =+F47 | H47: =+G47 | I47: =+H47 | J47: 0 | K47: 0 | L47: 0 | M47: 0 | N47: 0 | O47: 0 | P47: 0 | Q47: 0 | R47: 0 | S47: 0 | T47: 0 | U47: 0 | V47: 0 | W47: 0 | X47: 0 | Y47: 0 | Z47: 0 | AA47: 0 | AB47: 0 | AC47: 0 | AD47: 0 | AE47: 0 | AF47: 0 | AG47: 0 | AH47: 0 | AI47: 0 | AJ47: =SUM(C47:AI47) | AK47: =B47-AJ47
A48: Flores (Materiales Const. Compatty 680m2) | B48: =12166.54+8860.75 | D48: 0 | E48: 0 | F48: 0 | G48: =+F48 | H48: =+G48 | I48: =+H48 | J48: 0 | K48: 0 | L48: 0 | M48: 0 | N48: 0 | O48: 0 | P48: 0 | Q48: 0 | R48: 0 | S48: 0 | T48: 0 | U48: 0 | V48: 0 | W48: 0 | X48: 0 | Y48: 0 | Z48: 0 | AA48: 0 | AB48: 0 | AC48: 0 | AD48: 0 | AE48: 0 | AF48: 0 | AG48: 0 | AH48: 0 | AI48: 0 | AJ48: =SUM(C48:AI48) | AK48: =B48-AJ48
A49: Estructura Metalica - Sra Ruth Mano de Obra - Bod.680m2 Compatty | B49: 6500 | D49: 0 | E49: 0 | F49: 0 | G49: 928.57143 | H49: 928.57143 | I49: 928.57143 | J49: 928.57143 | K49: 928.57143 | L49: 928.57 | M49: 0 | N49: 0 | O49: 0 | P49: 0 | Q49: 0 | R49: 0 | S49: 0 | T49: 0 | U49: 0 | V49: 0 | W49: 0 | X49: 0 | Y49: 0 | Z49: 0 | AA49: 0 | AB49: 0 | AC49: 0 | AD49: 0 | AE49: 0 | AF49: 0 | AG49: 0 | AH49: 0 | AI49: 0 | AJ49: =SUM(C49:AI49) | AK49: =B49-AJ49
A50: 14 tubos redondos bpdega 680m2 | B50: 6500 | D50: 0 | E50: 0 | F50: 0 | G50: 0 | H50: 0 | I50: 0 | J50: 0 | K50: 0 | L50: 0 | M50: 0 | N50: 0 | O50: 0 | P50: 0 | Q50: 0 | R50: 0 | S50: 0 | T50: 0 | U50: 0 | V50: 0 | W50: 0 | X50: 0 | Y50: 0 | Z50: 0 | AA50: 0 | AB50: 0 | AC50: 0 | AD50: 0 | AE50: 0 | AF50: 0 | AG50: 0 | AH50: 0 | AI50: 0 | AJ50: =SUM(C50:AI50) | AK50: =B50-AJ50
A51: Estructura Metalica - Sra Ruth Materiales Obra - Bod.680m2 Compatty | B51: 12000 | D51: 0 | E51: 0 | F51: 0 | G51: 0 | H51: 4450.18 | I51: 0 | J51: 0 | K51: 7549.82 | L51: 0 | M51: 0 | N51: 0 | O51: 0 | P51: 0 | Q51: 0 | R51: 0 | S51: 0 | T51: 0 | U51: 0 | V51: 0 | W51: 0 | X51: 0 | Y51: 0 | Z51: 0 | AA51: 0 | AB51: 0 | AC51: 0 | AD51: 0 | AE51: 0 | AF51: 0 | AG51: 0 | AH51: 0 | AI51: 0 | AJ51: =SUM(C51:AI51) | AK51: =B51-AJ51
A52: Chinchi Mano de Obra y Materiales Bodegas 680 m2 | B52: 0 | D52: 0 | E52: 0 | F52: 0 | G52: 0 | H52: 0 | I52: 0 | J52: 0 | K52: 0 | L52: 0 | M52: 0 | N52: 0 | O52: 0 | P52: 0 | Q52: 0 | R52: 0 | S52: 0 | T52: 0 | U52: 0 | V52: 0 | W52: 0 | X52: 0 | Y52: 0 | Z52: 0 | AA52: 0 | AB52: 0 | AC52: 0 | AD52: 0 | AE52: 0 | AF52: 0 | AG52: 0 | AH52: 0 | AI52: 0 | AJ52: =SUM(C52:AI52) | AK52: =B52-AJ52
A53: SUBTOTAL EGRESOS DE OBRA DE BODEGA 680 M2 | B53: =+SUM(B47:B52) | C53: =+SUM(B47:B52)/680
A54: Ruth - Mano de Obra - Paso vial | B54: =1380+1322.5 | D54: 0 | E54: =1190.25+300 | F54: 621 | G54: 0 | H54: 0 | I54: 0 | J54: 0 | K54: 0 | L54: 0 | M54: 0 | N54: 0 | O54: 0 | P54: 0 | Q54: 0 | R54: 0 | S54: 0 | T54: 0 | U54: 0 | V54: 0 | W54: 0 | X54: 0 | Y54: 0 | Z54: 0 | AA54: 0 | AB54: 0 | AC54: 0 | AD54: 0 | AE54: 0 | AF54: 0 | AG54: 0 | AH54: 0 | AI54: 0 | AJ54: =SUM(C54:AI54) | AK54: =B54-AJ54
A55: Ruth - Materiales - Paso vial | B55: =125.03+1133.43+4450.18 | D55: 0 | E55: 0 | F55: 0 | G55: 0 | H55: 0 | I55: =4372.73-20.66+525.85 | J55: 0 | K55: 0 | L55: 0 | M55: 0 | N55: 0 | O55: 0 | P55: 0 | Q55: 0 | R55: 0 | S55: 0 | T55: 0 | U55: 0 | V55: 0 | W55: 0 | X55: 0 | Y55: 0 | Z55: 0 | AA55: 0 | AB55: 0 | AC55: 0 | AD55: 0 | AE55: 0 | AF55: 0 | AG55: 0 | AH55: 0 | AI55: 0 | AJ55: =SUM(C55:AI55) | AK55: =B55-AJ55
A56: Flores (Mano de obra Enblocado y Enlucido de Paso Vial) | B56: 3450 | D56: 0 | E56: =+B56*30% | F56: 1725 | G56: =+B56*30% | H56: 0 | I56: 0 | J56: 0 | K56: 0 | L56: 0 | M56: 0 | N56: 0 | O56: 0 | P56: 0 | Q56: 0 | R56: 0 | S56: 0 | T56: 0 | U56: 0 | V56: 0 | W56: 0 | X56: 0 | Y56: 0 | Z56: 0 | AA56: 0 | AB56: 0 | AC56: 0 | AD56: 0 | AE56: 0 | AF56: 0 | AG56: 0 | AH56: 0 | AI56: 0 | AJ56: =SUM(C56:AI56) | AK56: =B56-AJ56
A57: Flores (MaterialesEnblocado y Enlucido de Paso Vial) | B57: 2643.85 | D57: 0 | E57: 0 | F57: 0 | G57: 0 | H57: 0 | I57: 0 | J57: 0 | K57: 0 | L57: 0 | M57: 0 | N57: 0 | O57: 0 | P57: 0 | Q57: 0 | R57: 0 | S57: 0 | T57: =SUM(D57:S57) | U57: 2643.85 | V57: 0 | W57: 0 | X57: 0 | Y57: 0 | Z57: 0 | AA57: 0 | AB57: 0 | AC57: 0 | AD57: 0 | AE57: 0 | AF57: 0 | AG57: 0 | AH57: 0 | AI57: 0 | AJ57: =SUM(C57:AI57) | AK57: =B57-AJ57
A58: SUBTOTAL EGRESOS DE OBRA DE PASO VIAL | B58: =+SUM(B54:B57) | C58: =+SUM(B54:B57)/200
A59: Adoquinado — mano de obra | B59: 40089 | D59: 0 | E59: 0 | F59: 0 | G59: 0 | H59: 0 | I59: 0 | J59: 0 | K59: 0 | L59: 0 | M59: 0 | N59: 0 | O59: 0 | P59: 0 | Q59: 0 | R59: 0 | S59: 0 | T59: 0 | U59: 0 | V59: 0 | W59: 0 | X59: 0 | Y59: 0 | Z59: 0 | AA59: 0 | AB59: 0 | AC59: 0 | AD59: 0 | AE59: 0 | AF59: 0 | AG59: =+AF59 | AH59: =+AG59 | AI59: =+AH59 | AJ59: =SUM(C59:AI59) | AK59: =B59-AJ59
A60: Adoquinado — material | B60: 80568 | D60: 0 | E60: 0 | F60: 0 | G60: 0 | H60: 0 | I60: 0 | J60: 0 | K60: 0 | L60: 0 | M60: 0 | N60: 0 | O60: 0 | P60: 0 | Q60: 0 | R60: 0 | S60: 0 | T60: 0 | U60: 0 | V60: 0 | W60: 0 | X60: 0 | Y60: 0 | Z60: 0 | AA60: 0 | AB60: 0 | AC60: 0 | AD60: 0 | AE60: 0 | AF60: 0 | AG60: =+AF60 | AH60: =+AG60 | AI60: =+AH60 | AJ60: =SUM(C60:AI60) | AK60: =B60-AJ60
A61: SUBTOTAL EGRESOS DE OBRA DE ADOQUINADO - 6000 M2 | B61: =+SUM(B59:B60) | C61: =+B61/6000
A62: Remodelación 900m2 | B62: =900*40 | C62: =+B62/900 | D62: 0 | E62: 0 | F62: 0 | G62: 0 | H62: 0 | I62: 0 | J62: 0 | K62: 0 | L62: =+B62/6 | M62: =+L62 | N62: =+M62 | O62: =+N62/2 | P62: =+N62 | Q62: =+P62 | R62: =+O62 | S62: 0 | T62: 0 | U62: 0 | V62: 0 | W62: 0 | X62: 0 | Y62: 0 | Z62: 0 | AA62: 0 | AB62: 0 | AC62: 0 | AD62: 0 | AE62: 0 | AF62: 0 | AG62: 0 | AH62: 0 | AI62: 0 | AJ62: =SUM(D62:AI62) | AK62: =B62-AJ62
A63: Bodegas nuevas 432m2 | B63: =432*C36 | C63: =+B63/432 | D63: 0 | E63: 0 | F63: 0 | G63: 0 | H63: 0 | I63: 0 | J63: 0 | K63: 0 | L63: 0 | M63: 0 | N63: 0 | O63: 0 | P63: 0 | Q63: 0 | R63: 0 | S63: 0 | T63: 0 | U63: 0 | V63: 0 | W63: 0 | X63: 0 | Y63: =+B63/8 | Z63: =+Y63 | AA63: =+Z63 | AB63: =+AA63 | AC63: =+AB63 | AD63: =+AC63 | AE63: =+AD63 | AF63: =+AE63 | AG63: 0 | AH63: 0 | AI63: 0 | AJ63: =SUM(D63:AI63) | AK63: =B63-AJ63
A64: Readecuación 750m2 | B64: =750*C36 | C64: =+B64/750 | D64: 0 | E64: 0 | F64: 0 | G64: 0 | H64: 0 | I64: 0 | J64: 0 | K64: 0 | L64: =+B64/12 | M64: =+L64 | N64: =+M64 | O64: =+N64/2 | P64: =+N64 | Q64: =+P64 | R64: =+Q64 | S64: =+R64 | T64: =+S64 | U64: =+T64 | V64: =+U64 | W64: =+V64 | X64: =+O64 | Y64: 0 | Z64: 0 | AA64: 0 | AB64: 0 | AC64: 0 | AD64: 0 | AE64: 0 | AF64: 0 | AG64: 0 | AH64: 0 | AI64: 0 | AJ64: =SUM(D64:AI64) | AK64: =B64-AJ64
A65: Bodegas nuevas 600m2 | B65: =600*C36 | C65: =+B65/600 | D65: 0 | E65: 0 | F65: 0 | G65: 0 | H65: 0 | I65: 0 | J65: 0 | K65: 0 | L65: 0 | M65: 0 | N65: 0 | O65: 0 | P65: 0 | Q65: 0 | R65: 0 | S65: 0 | T65: 0 | U65: 0 | V65: 0 | W65: 0 | X65: =+B65/12 | Y65: =+X65 | Z65: =+Y65 | AA65: =+Z65 | AB65: =+AA65 | AC65: =+AB65 | AD65: =+AC65 | AE65: =+AD65 | AF65: =+AE65 | ... AI65: =+AH65 | AJ65: =SUM(D65:AI65) | AK65: =B65-AJ65
A66: SUBTOTAL EGRESOS DE OBRA | B66: =+B65+B64+B63+B62+B61+B58+B53+B46+B36 | C66: =+(B66-B61)/(600+750+432+900+680+150+1300) | D66: =SUM(D23:D65) | E66: =SUM(E23:E65) | F66: =SUM(F23:F65) | G66: =SUM(G23:G65) | H66: =SUM(H23:H65) | I66: =SUM(I23:I65) | J66: =SUM(J23:J65) | K66: =SUM(K23:K65) | ... AK66: =SUM(AK23:AK65)
A68: TOTAL EGRESOS (fijos + obra) | D68: =D21+D66 | E68: =E21+E66 | F68: =F21+F66 | G68: =G21+G66 | H68: =H21+H66 | I68: =I21+I66 | J68: =J21+J66 | K68: =K21+K66 | ... AI68: =AI21+AI66
A69: FLUJO NETO DE LA SEMANA | D69: =D11-D68 | E69: =E11-E68 | F69: =F11-F68 | G69: =G11-G68 | H69: =H11-H68 | I69: =I11-I68 | J69: =J11-J68 | K69: =K11-K68 | ... AI69: =AI11-AI68
A70: SALDO FINAL DE CAJA | D70: =D6+D69 | E70: =E6+E69 | F70: =F6+F69 | G70: =G6+G69 | H70: =H6+H69 | I70: =I6+I69 | J70: =J6+J69 | K70: =K6+K69 | ... AI70: =AI6+AI69
A72: Caja mínima de seguridad (referencia) | D72: =PARAMETROS!$B$28 | E72: =PARAMETROS!$B$28 | F72: =PARAMETROS!$B$28 | G72: =PARAMETROS!$B$28 | H72: =PARAMETROS!$B$28 | I72: =PARAMETROS!$B$28 | J72: =PARAMETROS!$B$28 | K72: =PARAMETROS!$B$28 | ... AI72: =PARAMETROS!$B$28
A73: Colchón sobre el mínimo (saldo final − mínimo) | D73: =D70-D72 | E73: =E70-E72 | F73: =F70-F72 | G73: =G70-G72 | H73: =H70-H72 | I73: =I70-I72 | J73: =J70-J72 | K73: =K70-K72 | ... AI73: =AI70-AI72
A74: ESTADO DE LA SEMANA | D74: =IF(D70<0,"🔴 NEGATIVO",IF(D70<D72,"🟠 ALERTA","🟢 OK")) | E74: =IF(E70<0,"🔴 NEGATIVO",IF(E70<E72,"🟠 ALERTA","🟢 OK")) | F74: =IF(F70<0,"🔴 NEGATIVO",IF(F70<F72,"🟠 ALERTA","🟢 OK")) | G74: =IF(G70<0,"🔴 NEGATIVO",IF(G70<G72,"🟠 ALERTA","🟢 OK")) | H74: =IF(H70<0,"🔴 NEGATIVO",IF(H70<H72,"🟠 ALERTA","🟢 OK")) | I74: =IF(I70<0,"🔴 NEGATIVO",IF(I70<I72,"🟠 ALERTA","🟢 OK")) | J74: =IF(J70<0,"🔴 NEGATIVO",IF(J70<J72,"🟠 ALERTA","🟢 OK")) | K74: =IF(K70<0,"🔴 NEGATIVO",IF(K70<K72,"🟠 ALERTA","🟢 OK")) | ... AI74: =IF(AI70<0,"🔴 NEGATIVO",IF(AI70<AI72,"🟠 ALERTA","🟢 OK"))
A76: DÉFICIT PROYECTADO — mirando 1 semana adelante (plazo Agroaéreo) | D76: =MIN(0,E70-E72) | E76: =MIN(0,F70-F72) | F76: =MIN(0,G70-G72) | G76: =MIN(0,H70-H72) | H76: =MIN(0,I70-I72) | I76: =MIN(0,J70-J72) | J76: =MIN(0,K70-K72) | K76: =MIN(0,L70-L72) | ... AI76: =MIN(0,AJ70-AJ72)
A77: ➤ ACCIÓN: SOLICITAR A AGROAÉREO ESTA SEMANA | D77: =IF(D76<0,"Pedir "&TEXT(-D76,"$#,#0")&" ahora para SEM 38","No se requiere") | E77: =IF(E76<0,"Pedir "&TEXT(-E76,"$#,#0")&" ahora para SEM 39","No se requiere") | F77: =IF(F76<0,"Pedir "&TEXT(-F76,"$#,#0")&" ahora para SEM 39","No se requiere") | G77: =IF(G76<0,"Pedir "&TEXT(-G76,"$#,#0")&" ahora para SEM 41","No se requiere") | H77: =IF(H76<0,"Pedir "&TEXT(-H76,"$#,#0")&" ahora para SEM 42","No se requiere") | I77: =IF(I76<0,"Pedir "&TEXT(-I76,"$#,#0")&" ahora para SEM 43","No se requiere") | J77: =IF(J76<0,"Pedir "&TEXT(-J76,"$#,#0")&" ahora para SEM 44","No se requiere") | K77: =IF(K76<0,"Pedir "&TEXT(-K76,"$#,#0")&" ahora para SEM 45","No se requiere") | L77: =IF(L76<0,"Pedir "&TEXT(-L76,"$#,#0")&" ahora para SEM 46","No se requiere") | M77: =IF(M76<0,"Pedir "&TEXT(-M76,"$#,#0")&" ahora para SEM 47","No se requiere") | N77: =IF(N76<0,"Pedir "&TEXT(-N76,"$#,#0")&" ahora para SEM 48","No se requiere") | O77: =IF(O76<0,"Pedir "&TEXT(-O76,"$#,#0")&" ahora para SEM 49","No se requiere") | P77: =IF(P76<0,"Pedir "&TEXT(-P76,"$#,#0")&" ahora para SEM 50","No se requiere") | Q77: =IF(Q76<0,"Pedir "&TEXT(-Q76,"$#,#0")&" ahora para SEM 51","No se requiere") | R77: =IF(R76<0,"Pedir "&TEXT(-R76,"$#,#0")&" ahora para SEM 52","No se requiere") | S77: =IF(S76<0,"Pedir "&TEXT(-S76,"$#,#0")&" ahora para SEM 52","No se requiere") | T77: =IF(T76<0,"Pedir "&TEXT(-T76,"$#,#0")&" ahora para SEM 52","No se requiere") | U77: =IF(U76<0,"Pedir "&TEXT(-U76,"$#,#0")&" ahora para SEM 52","No se requiere") | V77: =IF(V76<0,"Pedir "&TEXT(-V76,"$#,#0")&" ahora para SEM 52","No se requiere") | W77: =IF(W76<0,"Pedir "&TEXT(-W76,"$#,#0")&" ahora para SEM 52","No se requiere") | X77: =IF(X76<0,"Pedir "&TEXT(-X76,"$#,#0")&" ahora para SEM 52","No se requiere") | Y77: =IF(Y76<0,"Pedir "&TEXT(-Y76,"$#,#0")&" ahora para SEM 52","No se requiere") | ... AI77: =IF(AI76<0,"Pedir "&TEXT(-AI76,"$#,#0")&" ahora para SEM 52","No se requiere")

Sheet ESCENARIOS
A1: ESCENARIOS DE CAJA — SEM 37-2026 a SEM 16-2027
A2: Todo se calcula desde 'FLUJO SEMANAL (2)' y PARAMETROS. A = flujo tal como está. B = egresos fijos al promedio real de PARAMETROS (3.818/sem). C = B + septiembre con ingreso normal.
A4: CONCEPTO | B4: ='FLUJO SEMANAL (2)'!D4 | C4: ='FLUJO SEMANAL (2)'!E4 | D4: ='FLUJO SEMANAL (2)'!F4 | E4: ='FLUJO SEMANAL (2)'!G4 | F4: ='FLUJO SEMANAL (2)'!H4 | G4: ='FLUJO SEMANAL (2)'!I4 | H4: ='FLUJO SEMANAL (2)'!J4 | I4: ='FLUJO SEMANAL (2)'!K4 | ... AG4: ='FLUJO SEMANAL (2)'!AI4
B5: ='FLUJO SEMANAL (2)'!D5 | C5: ='FLUJO SEMANAL (2)'!E5 | D5: ='FLUJO SEMANAL (2)'!F5 | E5: ='FLUJO SEMANAL (2)'!G5 | F5: ='FLUJO SEMANAL (2)'!H5 | G5: ='FLUJO SEMANAL (2)'!I5 | H5: ='FLUJO SEMANAL (2)'!J5 | I5: ='FLUJO SEMANAL (2)'!K5 | ... AG5: ='FLUJO SEMANAL (2)'!AI5
A6: ESCENARIO A
A7: Flujo neto de la semana (A) | B7: ='FLUJO SEMANAL (2)'!D69 | C7: ='FLUJO SEMANAL (2)'!E69 | D7: ='FLUJO SEMANAL (2)'!F69 | E7: ='FLUJO SEMANAL (2)'!G69 | F7: ='FLUJO SEMANAL (2)'!H69 | G7: ='FLUJO SEMANAL (2)'!I69 | H7: ='FLUJO SEMANAL (2)'!J69 | I7: ='FLUJO SEMANAL (2)'!K69 | ... AG7: ='FLUJO SEMANAL (2)'!AI69
A8: A · SALDO FINAL — flujo tal como está | B8: ='FLUJO SEMANAL (2)'!D70 | C8: ='FLUJO SEMANAL (2)'!E70 | D8: ='FLUJO SEMANAL (2)'!F70 | E8: ='FLUJO SEMANAL (2)'!G70 | F8: ='FLUJO SEMANAL (2)'!H70 | G8: ='FLUJO SEMANAL (2)'!I70 | H8: ='FLUJO SEMANAL (2)'!J70 | I8: ='FLUJO SEMANAL (2)'!K70 | ... AG8: ='FLUJO SEMANAL (2)'!AI70
A9: ESCENARIO B
A10: Ajuste: fijos PARAMETROS − fijos cargados | B10: =PARAMETROS!$B$52-'FLUJO SEMANAL (2)'!D21 | C10: =PARAMETROS!$B$52-'FLUJO SEMANAL (2)'!E21 | D10: =PARAMETROS!$B$52-'FLUJO SEMANAL (2)'!F21 | E10: =PARAMETROS!$B$52-'FLUJO SEMANAL (2)'!G21 | F10: =PARAMETROS!$B$52-'FLUJO SEMANAL (2)'!H21 | G10: =PARAMETROS!$B$52-'FLUJO SEMANAL (2)'!I21 | H10: =PARAMETROS!$B$52-'FLUJO SEMANAL (2)'!J21 | I10: =PARAMETROS!$B$52-'FLUJO SEMANAL (2)'!K21 | ... AG10: =PARAMETROS!$B$52-'FLUJO SEMANAL (2)'!AI21
A11: B · SALDO FINAL — fijos al promedio real | B11: =PARAMETROS!$B$11+B7-B10 | C11: =B11+C7-C10 | D11: =C11+D7-D10 | E11: =D11+E7-E10 | F11: =E11+F7-F10 | G11: =F11+G7-G10 | H11: =G11+H7-H10 | I11: =H11+I7-I10 | J11: =I11+J7-J10 | ... AG11: =AF11+AG7-AG10
A12: ESCENARIO C
A13: Ajuste: septiembre a ingreso normal (solo SEM 37) | B13: =PARAMETROS!$B$53-SUM('FLUJO SEMANAL (2)'!$D$8:$F$8) | C13: =0 | D13: =0 | E13: =0 | F13: =0 | G13: =0 | H13: =0 | I13: =0 | J13: =0 | ... AG13: =0
A14: C · SALDO FINAL — B + septiembre normal | B14: =PARAMETROS!$B$11+B7-B10+B13 | C14: =B14+C7-C10+C13 | D14: =C14+D7-D10+D13 | E14: =D14+E7-E10+E13 | F14: =E14+F7-F10+F13 | G14: =F14+G7-G10+G13 | H14: =G14+H7-H10+H13 | I14: =H14+I7-I10+I13 | J14: =I14+J7-J10+J13 | ... AG14: =AF14+AG7-AG10+AG13
A17: RESUMEN
A18: Escenario | B18: Saldo mínimo | C18: Saldo final SEM 16 | D18: Semanas bajo caja mínima | E18: Semanas con caja negativa | F18: Fondeo adicional para no bajar de la caja mínima
A19: A · Flujo tal como está | B19: =MIN($B$8:$AG$8) | C19: =AG8 | D19: =COUNTIF($B$8:$AG$8,"<"&PARAMETROS!$B$28) | E19: =COUNTIF($B$8:$AG$8,"<0") | F19: =MAX(0,PARAMETROS!$B$28-B19)
A20: B · Fijos al promedio real | B20: =MIN($B$11:$AG$11) | C20: =AG11 | D20: =COUNTIF($B$11:$AG$11,"<"&PARAMETROS!$B$28) | E20: =COUNTIF($B$11:$AG$11,"<0") | F20: =MAX(0,PARAMETROS!$B$28-B20)
A21: C · B + septiembre normal | B21: =MIN($B$14:$AG$14) | C21: =AG14 | D21: =COUNTIF($B$14:$AG$14,"<"&PARAMETROS!$B$28) | E21: =COUNTIF($B$14:$AG$14,"<0") | F21: =MAX(0,PARAMETROS!$B$28-B21)
A23: Lectura: el fondeo adicional de la columna F es lo que habría que sumar a los 90.000 de Agroaéreo ya programados para no perforar la caja mínima en ninguna semana, si ese escenario ocurre.
A24: Pendiente del usuario: decidir si la base real de egresos fijos es la de PARAMETROS (B) o la cargada semana a semana (A), y confirmar si los cobros de septiembre son reales (A/B) o proyectados (C).

Sheet GANTT OBRAS
B2: DIAGRAMA DE GANTT — OBRAS DE BODEGAS MOBIJUESA · septiembre 2026 a abril 2027
B3: Cada barra va del mes de inicio al mes de fin de la obra según el calendario de pagos de FLUJO SEMANAL (2) (semanas 37 a 16). El texto dentro de la barra es vivo: m², costo total (columna B de los subtotales de obra) y costo por m² (columna C). Si cambia un costo en el flujo, la barra se actualiza; si cambia el calendario, mueva las columnas Inicio/Fin (amarillas).
B4: Nº de mes → | C4: Inicio | D4: Fin | F4: 1 | G4: 2 | H4: 3 | I4: 4 | J4: 5 | K4: 6 | L4: 7 | M4: 8
B5: OBRA / BODEGA | C5: m² | D5: Costo total | E5: $/m² | F5: 46291 | G5: 46321 | H5: 46352 | I5: dic-26 | J5: ene-27 | K5: 46080 | L5: 46108 | M5: abr-27 | N5: Observación
B6: Bodega 1.300 m² (Bod. 16-17: estructura Tapia, cimentación y piso Flores, pozo, 5 puertas) | C6: 1300 | D6: ='FLUJO SEMANAL (2)'!B36 | E6: =IF(C6=0,0,D6/C6) | F6: =TEXT(C6,"#.##0")&" m² · "&TEXT(D6,"$#.##0")&" · "&TEXT(E6,"$#.##0,00")&"/m²" | N6: Ejecutado antes de SEM 37: $111.272 de $145.123; remanente sep-nov
B7: Bodega 150 m² (contenedores + estructura metálica) | C7: 150 | D7: ='FLUJO SEMANAL (2)'!B46 | E7: =IF(C7=0,0,D7/C7) | F7: =TEXT(C7,"#.##0")&" m² · "&TEXT(D7,"$#.##0")&" · "&TEXT(E7,"$#.##0,00")&"/m²"
B8: Bodega Compatty 680 m² (Flores + estructura Sra. Ruth) | C8: 680 | D8: ='FLUJO SEMANAL (2)'!B53 | E8: =IF(C8=0,0,D8/C8) | F8: =TEXT(C8,"#.##0")&" m² · "&TEXT(D8,"$#.##0")&" · "&TEXT(E8,"$#.##0,00")&"/m²" | N8: 14 tubos ($6.500) aún sin programar
B9: Paso vial 200 m² (Ruth + enblocado/enlucido Flores) | C9: 200 | D9: ='FLUJO SEMANAL (2)'!B58 | E9: =IF(C9=0,0,D9/C9) | F9: =TEXT(C9,"#.##0")&" m² · "&TEXT(D9,"$#.##0")&" · "&TEXT(E9,"$#.##0,00")&"/m²"
B10: Remodelación 900 m² ($40/m²) | C10: 900 | D10: ='FLUJO SEMANAL (2)'!B62 | E10: =IF(C10=0,0,D10/C10) | H10: =TEXT(C10,"#.##0")&" m² · "&TEXT(D10,"$#.##0")&" · "&TEXT(E10,"$#.##0,00")&"/m²"
B11: Readecuación 750 m² (a $111,63/m² de la bodega 1.300) | C11: 750 | D11: ='FLUJO SEMANAL (2)'!B64 | E11: =IF(C11=0,0,D11/C11) | H11: =TEXT(C11,"#.##0")&" m² · "&TEXT(D11,"$#.##0")&" · "&TEXT(E11,"$#.##0,00")&"/m²"
B12: Bodegas nuevas 600 m² | C12: 600 | D12: ='FLUJO SEMANAL (2)'!B65 | E12: =IF(C12=0,0,D12/C12) | K12: =TEXT(C12,"#.##0")&" m² · "&TEXT(D12,"$#.##0")&" · "&TEXT(E12,"$#.##0,00")&"/m²"
B13: Bodegas nuevas 432 m² | C13: 432 | D13: ='FLUJO SEMANAL (2)'!B63 | E13: =IF(C13=0,0,D13/C13) | K13: =TEXT(C13,"#.##0")&" m² · "&TEXT(D13,"$#.##0")&" · "&TEXT(E13,"$#.##0,00")&"/m²"
B14: Adoquinado 6.000 m² ($20,11/m²) | C14: 6000 | D14: ='FLUJO SEMANAL (2)'!B61 | E14: =IF(C14=0,0,D14/C14) | F14: ="SIN PROGRAMAR EN EL HORIZONTE — "&TEXT(D14,"$#.##0")&" ("&TEXT(E14,"$#.##0,00")&"/m²)" | N14: SIN PROGRAMAR en el horizonte: $120.657 fuera del flujo (columna DIFERENCIA)
B15: TOTAL OBRAS (con adoquinado) | C15: =SUM(C6:C14) | D15: =SUM(D6:D14) | E15: =IF(C15=0,0,D15/C15)
B16: Programado en el flujo (SEM 37 a SEM 16) / Diferencia sin programar | D16: ='FLUJO SEMANAL (2)'!AJ66 | E16: ='FLUJO SEMANAL (2)'!AK66
B17: Ya ejecutado antes de la SEM 37 (columna SALDO INICIAL de las filas de obra) | D17: =SUM('FLUJO SEMANAL (2)'!C23:C35)+SUM('FLUJO SEMANAL (2)'!C37:C45)+SUM('FLUJO SEMANAL (2)'!C47:C52)+SUM('FLUJO SEMANAL (2)'!C54:C57)
B19: Egreso de obra programado por mes (suma de SUBTOTAL EGRESOS DE OBRA, fila 65 del flujo) | F19: =SUM('FLUJO SEMANAL (2)'!D66:F66) | G19: =SUM('FLUJO SEMANAL (2)'!G66:J66) | H19: =SUM('FLUJO SEMANAL (2)'!K66:O66) | I19: =SUM('FLUJO SEMANAL (2)'!P66:S66) | J19: =SUM('FLUJO SEMANAL (2)'!T66:W66) | K19: =SUM('FLUJO SEMANAL (2)'!X66:AA66) | L19: =SUM('FLUJO SEMANAL (2)'!AB66:AE66) | M19: =SUM('FLUJO SEMANAL (2)'!AF66:AI66)
B20: Saldo final de caja al cierre de cada mes (fila 69 del flujo) | F20: ='FLUJO SEMANAL (2)'!F70 | G20: ='FLUJO SEMANAL (2)'!J70 | H20: ='FLUJO SEMANAL (2)'!O70 | I20: ='FLUJO SEMANAL (2)'!S70 | J20: ='FLUJO SEMANAL (2)'!W70 | K20: ='FLUJO SEMANAL (2)'!AA70 | L20: ='FLUJO SEMANAL (2)'!AE70 | M20: ='FLUJO SEMANAL (2)'!AI70
B21: Aportes de Agroaéreo programados en el mes (fila 9 del flujo) | F21: =SUM('FLUJO SEMANAL (2)'!D9:F9) | G21: =SUM('FLUJO SEMANAL (2)'!G9:J9) | H21: =SUM('FLUJO SEMANAL (2)'!K9:O9) | I21: =SUM('FLUJO SEMANAL (2)'!P9:S9) | J21: =SUM('FLUJO SEMANAL (2)'!T9:W9) | K21: =SUM('FLUJO SEMANAL (2)'!X9:AA9) | L21: =SUM('FLUJO SEMANAL (2)'!AB9:AE9) | M21: =SUM('FLUJO SEMANAL (2)'!AF9:AI9)
B22: Ingreso operativo + otros ingresos del mes (filas 8 y 10 del flujo) | F22: =SUM('FLUJO SEMANAL (2)'!D8:F8)+SUM('FLUJO SEMANAL (2)'!D10:F10) | G22: =SUM('FLUJO SEMANAL (2)'!G8:J8)+SUM('FLUJO SEMANAL (2)'!G10:J10) | H22: =SUM('FLUJO SEMANAL (2)'!K8:O8)+SUM('FLUJO SEMANAL (2)'!K10:O10) | I22: =SUM('FLUJO SEMANAL (2)'!P8:S8)+SUM('FLUJO SEMANAL (2)'!P10:S10) | J22: =SUM('FLUJO SEMANAL (2)'!T8:W8)+SUM('FLUJO SEMANAL (2)'!T10:W10) | K22: =SUM('FLUJO SEMANAL (2)'!X8:AA8)+SUM('FLUJO SEMANAL (2)'!X10:AA10) | L22: =SUM('FLUJO SEMANAL (2)'!AB8:AE8)+SUM('FLUJO SEMANAL (2)'!AB10:AE10) | M22: =SUM('FLUJO SEMANAL (2)'!AF8:AI8)+SUM('FLUJO SEMANAL (2)'!AF10:AI10)

Sheet Estadística (2)
B3: =+'FLUJO SEMANAL (2)'!A4 | C3: =+'FLUJO SEMANAL (2)'!H5 | D3: =+'FLUJO SEMANAL (2)'!I5 | E3: =+'FLUJO SEMANAL (2)'!J5 | F3: =+'FLUJO SEMANAL (2)'!K5 | G3: =+'FLUJO SEMANAL (2)'!L5 | H3: =+'FLUJO SEMANAL (2)'!M5 | I3: =+'FLUJO SEMANAL (2)'!N5 | J3: =+'FLUJO SEMANAL (2)'!O5 | ... AD3: =+'FLUJO SEMANAL (2)'!AI5
B4: =+'FLUJO SEMANAL (2)'!A11 | C4: =+'FLUJO SEMANAL (2)'!H11 | D4: =+'FLUJO SEMANAL (2)'!I11 | E4: =+'FLUJO SEMANAL (2)'!J11 | F4: =+'FLUJO SEMANAL (2)'!K11 | G4: =+'FLUJO SEMANAL (2)'!L11 | H4: =+'FLUJO SEMANAL (2)'!M11 | I4: =+'FLUJO SEMANAL (2)'!N11 | J4: =+'FLUJO SEMANAL (2)'!O11 | ... AD4: =+'FLUJO SEMANAL (2)'!AI11
B5: =+'FLUJO SEMANAL (2)'!A68 | C5: =+'FLUJO SEMANAL (2)'!H68 | D5: =+'FLUJO SEMANAL (2)'!I68 | E5: =+'FLUJO SEMANAL (2)'!J68 | F5: =+'FLUJO SEMANAL (2)'!K68 | G5: =+'FLUJO SEMANAL (2)'!L68 | H5: =+'FLUJO SEMANAL (2)'!M68 | I5: =+'FLUJO SEMANAL (2)'!N68 | J5: =+'FLUJO SEMANAL (2)'!O68 | ... AD5: =+'FLUJO SEMANAL (2)'!AI68
B6: =+'FLUJO SEMANAL (2)'!A70 | C6: =+'FLUJO SEMANAL (2)'!H70 | D6: =+'FLUJO SEMANAL (2)'!I70 | E6: =+'FLUJO SEMANAL (2)'!J70 | F6: =+'FLUJO SEMANAL (2)'!K70 | G6: =+'FLUJO SEMANAL (2)'!L70 | H6: =+'FLUJO SEMANAL (2)'!M70 | I6: =+'FLUJO SEMANAL (2)'!N70 | J6: =+'FLUJO SEMANAL (2)'!O70 | ... AD6: =+'FLUJO SEMANAL (2)'!AI70
